{"draw":0,"recordsTotal":103,"recordsFiltered":103,"data":[{"Alamat":"Jl. Pengantin Ali No. 88, Ciracas\r\nKota Jakarta Timur, DKI Jakarta 13740","BAE":"","DataID":0,"Divisi":null,"EfekEmiten_EBA":false,"EfekEmiten_ETF":false,"EfekEmiten_Obligasi":true,"EfekEmiten_Saham":true,"EfekEmiten_SPEI":false,"Industri":"Pengelola & Pengembang Real Estat","SubIndustri":"Pengembang & Operator Real Estat","Email":"corsec@adcp.co.id","Fax":"(021) 228 220 81","id":0,"JenisEmiten":null,"KegiatanUsahaUtama":"Perhotelan dan Real Estate","KodeDivisi":null,"KodeEmiten":"ADCP","NamaEmiten":"PT Adhi Commuter Properti Tbk","NPKP":"","NPWP":"85.227.029.7-093.000","PapanPencatatan":"Utama","Sektor":"Properti & Real Estat","SubSektor":"Properti & Real Estat","TanggalPencatatan":"2021-05-21T00:00:00","Telepon":"(021) 228 229 80","Website":"www.adcp.co.id","Status":0,"Logo":"/Portals/0/StaticData/ListedCompanies/LogoEmiten/ADCP.jpg"},{"Alamat":"Jalan Raya Pasar Minggu Km. 18 Jakarta 12510","BAE":"","DataID":0,"Divisi":null,"EfekEmiten_EBA":false,"EfekEmiten_ETF":false,"EfekEmiten_Obligasi":true,"EfekEmiten_Saham":true,"EfekEmiten_SPEI":false,"Industri":"Konstruksi Bangunan","SubIndustri":"Konstruksi Bangunan","Email":"adhi@adhi.co.id","Fax":"021-7975311","id":0,"JenisEmiten":null,"KegiatanUsahaUtama":"Konstruksi","KodeDivisi":null,"KodeEmiten":"ADHI","NamaEmiten":"PT Adhi Karya (Persero) Tbk.","NPKP":"","NPWP":"01.001.610.3-051.000","PapanPencatatan":"Utama","Sektor":"Infrastruktur","SubSektor":"Konstruksi Bangunan","TanggalPencatatan":"2004-03-18T00:00:00","Telepon":"021-7975312","Website":"www.adhi.co.id","Status":0,"Logo":"/Portals/0/StaticData/ListedCompanies/LogoEmiten/ADHI.jpg"},{"Alamat":"Millennium Centennial Center Lantai 53, 56-61, Jl. Jenderal Sudirman Kav. 25 Jakarta 12920","BAE":"","DataID":0,"Divisi":null,"EfekEmiten_EBA":false,"EfekEmiten_ETF":false,"EfekEmiten_Obligasi":true,"EfekEmiten_Saham":true,"EfekEmiten_SPEI":false,"Industri":"Pembiayaan Konsumen","SubIndustri":"Pembiayaan Konsumen","Email":"af.corsec@adira.co.id","Fax":"021-3973 4949","id":0,"JenisEmiten":null,"KegiatanUsahaUtama":"Pembiayaan","KodeDivisi":null,"KodeEmiten":"ADMF","NamaEmiten":"Adira Dinamika Multi Finance Tbk","NPKP":"","NPWP":"01.346.494.6-091.000","PapanPencatatan":"Utama","Sektor":"Keuangan","SubSektor":"Jasa Pembiayaan","TanggalPencatatan":"2004-03-31T00:00:00","Telepon":"021-3973 3232, 021-3973 3322","Website":"www.adira.co.id","Status":0,"Logo":"/Portals/0/StaticData/ListedCompanies/LogoEmiten/ADMF.jpg"},{"Alamat":"Gedung UGM - Samator Pendidikan Tower A Lantai 5-6  Jl. Dr. Sahardjo No. 83, Manggarai Tebet, Jakarta Selatan 12850","BAE":"","DataID":0,"Divisi":null,"EfekEmiten_EBA":false,"EfekEmiten_ETF":false,"EfekEmiten_Obligasi":true,"EfekEmiten_Saham":true,"EfekEmiten_SPEI":false,"Industri":"Barang Kimia","SubIndustri":"Barang Kimia Dasar","Email":"corsec@anekagas.com","Fax":"021 - 83709911","id":0,"JenisEmiten":null,"KegiatanUsahaUtama":"memproduksi, memasarkan dan menjual berbagai macam gas","KodeDivisi":null,"KodeEmiten":"AGII","NamaEmiten":"PT Samator Indo Gas Tbk","NPKP":"","NPWP":"01.002.124.4-038.000","PapanPencatatan":"Utama","Sektor":"Barang Baku","SubSektor":"Barang Baku","TanggalPencatatan":"2016-09-28T00:00:00","Telepon":"021 - 83709111","Website":"www.anekagas.com","Status":0,"Logo":"/Portals/0/StaticData/ListedCompanies/LogoEmiten/AGII.jpg"},{"Alamat":"Menara BRILiaN Lt. 20 Jalan Gatot Subroto No. 177 A Kel. Menteng Dalam Kecamatan Tebet Jakarta Selatan DKI Jakarta","BAE":"","DataID":0,"Divisi":null,"EfekEmiten_EBA":false,"EfekEmiten_ETF":false,"EfekEmiten_Obligasi":true,"EfekEmiten_Saham":true,"EfekEmiten_SPEI":false,"Industri":"Bank","SubIndustri":"Bank","Email":"humas@bankraya.co.id","Fax":"021-50931494","id":0,"JenisEmiten":null,"KegiatanUsahaUtama":"Perbankan","KodeDivisi":null,"KodeEmiten":"AGRO","NamaEmiten":"PT Bank Raya Indonesia Tbk","NPKP":"","NPWP":"01.347.428.3-054.000","PapanPencatatan":"Utama","Sektor":"Keuangan","SubSektor":"Bank","TanggalPencatatan":"2003-08-08T00:00:00","Telepon":"021-50931300","Website":"bankraya.co.id","Status":0,"Logo":"/Portals/0/StaticData/ListedCompanies/LogoEmiten/AGRO.jpg"},{"Alamat":"Menara Astra Lantai 29, Jalan Jend. Sudirman Kav 5-6, Karet Tengsin, Jakarta Pusat 10220","BAE":"","DataID":0,"Divisi":null,"EfekEmiten_EBA":false,"EfekEmiten_ETF":false,"EfekEmiten_Obligasi":true,"EfekEmiten_Saham":true,"EfekEmiten_SPEI":false,"Industri":"Makanan Olahan","SubIndustri":"Makanan Olahan","Email":"corporate.secretary@fksfs.co.id","Fax":"021 - 50889838","id":0,"JenisEmiten":null,"KegiatanUsahaUtama":"Industri Mie","KodeDivisi":null,"KodeEmiten":"AISA","NamaEmiten":"PT FKS Food Sejahtera Tbk","NPKP":"-","NPWP":"01.504.513.1-054.000","PapanPencatatan":"Utama","Sektor":"Barang Konsumen Primer","SubSektor":"Makanan & Minuman","TanggalPencatatan":"1997-06-11T00:00:00","Telepon":"021 - 50889898","Website":"www.fksfs.co.id","Status":0,"Logo":"/Portals/0/StaticData/ListedCompanies/LogoEmiten/AISA.jpg"},{"Alamat":"AKR Tower Lt.26, Jl. Panjang No.5 Kebon Jeruk, Jakarta Barat 11530","BAE":"","DataID":0,"Divisi":null,"EfekEmiten_EBA":false,"EfekEmiten_ETF":false,"EfekEmiten_Obligasi":true,"EfekEmiten_Saham":true,"EfekEmiten_SPEI":false,"Industri":"Minyak & Gas","SubIndustri":"Penyimpanan & Distribusi Minyak & Gas","Email":"corporate.secretary@akr.co.id","Fax":"(021) 531 1185","id":0,"JenisEmiten":null,"KegiatanUsahaUtama":"Perdagangan dan Distribusi BBM dan Bahan Kimia Dasar","KodeDivisi":null,"KodeEmiten":"AKRA","NamaEmiten":"PT AKR Corporindo Tbk.","NPKP":"","NPWP":"01.132.905.9-092.000","PapanPencatatan":"Utama","Sektor":"Energi","SubSektor":"Minyak, Gas & Batu Bara","TanggalPencatatan":"1994-10-03T00:00:00","Telepon":"(021) 531 1110","Website":"www.akr.co.id","Status":0,"Logo":"/Portals/0/StaticData/ListedCompanies/LogoEmiten/AKRA.jpg"},{"Alamat":"Jl. Jalur Sutera Barat Kav. 9, Alam Sutera, Kota Tangerang, Prov. Banten","BAE":"","DataID":0,"Divisi":null,"EfekEmiten_EBA":false,"EfekEmiten_ETF":false,"EfekEmiten_Obligasi":true,"EfekEmiten_Saham":true,"EfekEmiten_SPEI":false,"Industri":"Perdagangan Ritel Barang Primer","SubIndustri":"Supermarket","Email":"corsec@sat.co.id / investor_relations@sat.co.id","Fax":"021-80821556","id":0,"JenisEmiten":null,"KegiatanUsahaUtama":"Retail Trade ","KodeDivisi":null,"KodeEmiten":"AMRT","NamaEmiten":"PT Sumber Alfaria Trijaya Tbk.","NPKP":"01.336.238.9-054.000","NPWP":"01.336.238.9-054.000","PapanPencatatan":"Utama","Sektor":"Barang Konsumen Primer","SubSektor":"Perdagangan Ritel Barang Primer","TanggalPencatatan":"2009-01-15T00:00:00","Telepon":"021-80821555","Website":"www.alfamart.co.id","Status":0,"Logo":"/Portals/0/StaticData/ListedCompanies/LogoEmiten/AMRT.jpg"},{"Alamat":"Gedung. Aneka Tambang \r\nJl. Letjen TB. Simatupang No. 1 \r\nJakarta 12530\r\n","BAE":"PT. Datindo Entrycom","DataID":0,"Divisi":null,"EfekEmiten_EBA":false,"EfekEmiten_ETF":false,"EfekEmiten_Obligasi":true,"EfekEmiten_Saham":true,"EfekEmiten_SPEI":false,"Industri":"Logam & Mineral","SubIndustri":"Logam & Mineral Lainnya","Email":"corsec@antam.com","Fax":"021-7812822","id":0,"JenisEmiten":null,"KegiatanUsahaUtama":"Metal and Mineral Mining ","KodeDivisi":null,"KodeEmiten":"ANTM","NamaEmiten":"Aneka Tambang Tbk.","NPKP":"","NPWP":"01.001.663.2-051.000","PapanPencatatan":"Utama","Sektor":"Barang Baku","SubSektor":"Barang Baku","TanggalPencatatan":"1997-11-27T00:00:00","Telepon":"021-7805119; 021-7891234 ; 021-7812635 \r\n","Website":"http://www.antam.com/","Status":0,"Logo":"/Portals/0/StaticData/ListedCompanies/LogoEmiten/ANTM.jpg"},{"Alamat":"Podomoro City - APL Tower, Lt. 45\r\nJl. Letjen. S. Parman Kav. 28\r\nJakarta 11470","BAE":"","DataID":0,"Divisi":null,"EfekEmiten_EBA":false,"EfekEmiten_ETF":false,"EfekEmiten_Obligasi":true,"EfekEmiten_Saham":true,"EfekEmiten_SPEI":false,"Industri":"Pengelola & Pengembang Real Estat","SubIndustri":"Pengembang & Operator Real Estat","Email":"APLN.SP@agungpodomoroland.com","Fax":"021-29034556","id":0,"JenisEmiten":null,"KegiatanUsahaUtama":"Pengembangan, pengelolaan dan penyewaan properti terpadu yang meliputi apartemen, perumahan, perhotelan, perkantoran, pertokoan, pusat perbelanjaan dan pusat rekreasi beserta fasilitasnya melalui Perseroan maupun Entitas Anak Perseroan","KodeDivisi":null,"KodeEmiten":"APLN","NamaEmiten":"PT Agung Podomoro Land Tbk.","NPKP":"-","NPWP":"02.380.812.4-054.000","PapanPencatatan":"Utama","Sektor":"Properti & Real Estat","SubSektor":"Properti & Real Estat","TanggalPencatatan":"2010-11-11T00:00:00","Telepon":"021-29034567","Website":"www.agungpodomoroland.com","Status":0,"Logo":"/Portals/0/StaticData/ListedCompanies/LogoEmiten/APLN.jpg"},{"Alamat":"Gedung Graha Kirana Lt. 6, Jl. Yos Sudarso No. 88, Sunter, Jakarta Utara 14350 – Indonesia ","BAE":"","DataID":0,"Divisi":null,"EfekEmiten_EBA":false,"EfekEmiten_ETF":false,"EfekEmiten_Obligasi":true,"EfekEmiten_Saham":true,"EfekEmiten_SPEI":false,"Industri":"Pengangkutan Darat Penumpang","SubIndustri":"Transportasi Jalanan","Email":"corporate.secretary@assarent.co.id","Fax":"6530 8822","id":0,"JenisEmiten":null,"KegiatanUsahaUtama":"Bergerak di bidang jasa penyewaan kendaraan bermotor/alat transportasi darat, jual beli kendaraan bekas, jasa pengurusan transportasi/logistik dan jasa penyediaan juru mudi melalui Entitas Anak","KodeDivisi":null,"KodeEmiten":"ASSA","NamaEmiten":"Adi Sarana Armada Tbk","NPKP":"0","NPWP":"01.955.213.2-054.000","PapanPencatatan":"Utama","Sektor":"Transportasi & Logistik","SubSektor":"Transportasi","TanggalPencatatan":"2012-11-12T00:00:00","Telepon":"6530 8811","Website":"www.assarent.co.id","Status":0,"Logo":"/Portals/0/StaticData/ListedCompanies/LogoEmiten/ASSA.jpg"},{"Alamat":"Menara Jamsostek Lantai 6, Jl, Gatot Subroto No. 38","BAE":"","DataID":0,"Divisi":null,"EfekEmiten_EBA":false,"EfekEmiten_ETF":false,"EfekEmiten_Obligasi":true,"EfekEmiten_Saham":true,"EfekEmiten_SPEI":false,"Industri":"Bank","SubIndustri":"Bank","Email":"helpdesk.corpsec@bankcapital.co.id","Fax":"(021)27938900","id":0,"JenisEmiten":null,"KegiatanUsahaUtama":"Perbankan","KodeDivisi":null,"KodeEmiten":"BACA","NamaEmiten":"PT Bank Capital Indonesia Tbk","NPKP":"","NPWP":"01.341.893.4-054.000","PapanPencatatan":"Pengembangan","Sektor":"Keuangan","SubSektor":"Bank","TanggalPencatatan":"2007-10-04T00:00:00","Telepon":"(021)27938989","Website":"www.bankcapital.co.id","Status":0,"Logo":"/Portals/0/StaticData/ListedCompanies/LogoEmiten/BACA.jpg"},{"Alamat":"Jln. Sunset Road, Lingkungan Abianbase, Kelurahan Kuta, Kecamatan Kuta,\r\n Kabupaten Badung, Bali 80361.\r\n","BAE":"","DataID":0,"Divisi":null,"EfekEmiten_EBA":false,"EfekEmiten_ETF":false,"EfekEmiten_Obligasi":true,"EfekEmiten_Saham":true,"EfekEmiten_SPEI":false,"Industri":"Jasa Telekomunikasi Nirkabel","SubIndustri":"Jasa Telekomunikasi Nirkabel","Email":"corporate.secretary@balitower.co.id","Fax":"(0361) 766059","id":0,"JenisEmiten":null,"KegiatanUsahaUtama":"Penyedia Menara Telekomunikasi, Jasa dan Jaringan Telekomunikasi ","KodeDivisi":null,"KodeEmiten":"BALI","NamaEmiten":"PT Bali Towerindo Sentra Tbk. ","NPKP":"","NPWP":"02.601.536.2-054.000","PapanPencatatan":"Utama","Sektor":"Infrastruktur","SubSektor":"Telekomunikasi","TanggalPencatatan":"2014-03-13T00:00:00","Telepon":"(0361) 767629","Website":"www.balitower.co.id","Status":0,"Logo":"/Portals/0/StaticData/ListedCompanies/LogoEmiten/BALI.jpg"},{"Alamat":"Menara BCA, Grand Indonesia\r\nJalan MH Thamrin No. 1\r\nJakarta 10310","BAE":"","DataID":0,"Divisi":null,"EfekEmiten_EBA":false,"EfekEmiten_ETF":false,"EfekEmiten_Obligasi":true,"EfekEmiten_Saham":true,"EfekEmiten_SPEI":false,"Industri":"Bank","SubIndustri":"Bank","Email":"investor_relations@bca.co.id","Fax":"021-23588300","id":0,"JenisEmiten":null,"KegiatanUsahaUtama":"Jasa Perbankan ","KodeDivisi":null,"KodeEmiten":"BBCA","NamaEmiten":"PT Bank Central Asia Tbk.","NPKP":"","NPWP":"01.308.449.6-091.000","PapanPencatatan":"Utama","Sektor":"Keuangan","SubSektor":"Bank","TanggalPencatatan":"2000-05-31T00:00:00","Telepon":"021-23588000","Website":"www.bca.co.id","Status":0,"Logo":"/Portals/0/StaticData/ListedCompanies/LogoEmiten/BBCA.jpg"},{"Alamat":"Gedung Bank KB Bukopin Jl. M.T. Haryono Kav.50-51 Jakarta 12770","BAE":"","DataID":0,"Divisi":null,"EfekEmiten_EBA":false,"EfekEmiten_ETF":false,"EfekEmiten_Obligasi":true,"EfekEmiten_Saham":true,"EfekEmiten_SPEI":false,"Industri":"Bank","SubIndustri":"Bank","Email":"investor.relations@kbbukopin.com; corsec@kbbukopin.com","Fax":"798-0625","id":0,"JenisEmiten":null,"KegiatanUsahaUtama":"Perbankan","KodeDivisi":null,"KodeEmiten":"BBKP","NamaEmiten":"PT Bank KB Bukopin Tbk","NPKP":"S-1PKP/WPJ.19/KP.0103/2021","NPWP":"01.367.605.1-091.000","PapanPencatatan":"Utama","Sektor":"Keuangan","SubSektor":"Bank","TanggalPencatatan":"2006-07-10T00:00:00","Telepon":"798-8266","Website":"www.kbbukopin.com","Status":0,"Logo":"/Portals/0/StaticData/ListedCompanies/LogoEmiten/BBKP.jpg"},{"Alamat":"Grha BNI Lantai 24\r\nJl. Jenderal Sudirman Kavling 1\r\nJakarta Pusat 10220","BAE":"","DataID":0,"Divisi":null,"EfekEmiten_EBA":false,"EfekEmiten_ETF":false,"EfekEmiten_Obligasi":true,"EfekEmiten_Saham":true,"EfekEmiten_SPEI":false,"Industri":"Bank","SubIndustri":"Bank","Email":"bni@bni.co.id","Fax":"021-2511961","id":0,"JenisEmiten":null,"KegiatanUsahaUtama":"Perbankan & kegiatan usaha penunjang lainnya","KodeDivisi":null,"KodeEmiten":"BBNI","NamaEmiten":"PT Bank Negara Indonesia (Persero) Tbk","NPKP":"","NPWP":"01.001.606.1-093.000","PapanPencatatan":"Utama","Sektor":"Keuangan","SubSektor":"Bank","TanggalPencatatan":"1996-11-25T00:00:00","Telepon":"021-2511946, 021-5728387","Website":"www.bni.co.id","Status":0,"Logo":"/Portals/0/StaticData/ListedCompanies/LogoEmiten/BBNI.jpg"},{"Alamat":"Gedung BRI I Lantai 20\r\nJl. Jenderal Sudirman Kav.44-46, Jakarta Pusat 10210","BAE":"","DataID":0,"Divisi":null,"EfekEmiten_EBA":false,"EfekEmiten_ETF":false,"EfekEmiten_Obligasi":true,"EfekEmiten_Saham":true,"EfekEmiten_SPEI":false,"Industri":"Bank","SubIndustri":"Bank","Email":"humas@bri.co.id; corsec@bri.co.id","Fax":"021 - 5752010; 5700916","id":0,"JenisEmiten":null,"KegiatanUsahaUtama":"Jasa Perbankan ","KodeDivisi":null,"KodeEmiten":"BBRI","NamaEmiten":"PT Bank Rakyat Indonesia (Persero) Tbk","NPKP":"-","NPWP":"01.001.608.7-093.000","PapanPencatatan":"Utama","Sektor":"Keuangan","SubSektor":"Bank","TanggalPencatatan":"2003-11-10T00:00:00","Telepon":"021 - 575 1966","Website":"www.bri.co.id","Status":0,"Logo":"/Portals/0/StaticData/ListedCompanies/LogoEmiten/BBRI.jpg"},{"Alamat":"Gedung Menara BTN, Jl.Gajah Mada No. 1, Jakarta 10130 ","BAE":"","DataID":0,"Divisi":null,"EfekEmiten_EBA":false,"EfekEmiten_ETF":false,"EfekEmiten_Obligasi":true,"EfekEmiten_Saham":true,"EfekEmiten_SPEI":false,"Industri":"Bank","SubIndustri":"Bank","Email":"achmad.chaerul@btn.co.id","Fax":"-","id":0,"JenisEmiten":null,"KegiatanUsahaUtama":"Bergerak Dalam Bidang Usaha Perbankan","KodeDivisi":null,"KodeEmiten":"BBTN","NamaEmiten":"PT Bank Tabungan Negara (Persero) Tbk","NPKP":"-","NPWP":"01.001.609.5-093.000","PapanPencatatan":"Utama","Sektor":"Keuangan","SubSektor":"Bank","TanggalPencatatan":"2009-12-17T00:00:00","Telepon":"021-6336789","Website":"www.btn.co.id","Status":0,"Logo":"/Portals/0/StaticData/ListedCompanies/LogoEmiten/BBTN.jpg"},{"Alamat":"MNC Financial Center Lt.21\r\nJl. Kebon Sirih No.21-27\r\nJakarta Pusat. 10340\r\nIndonesia","BAE":"","DataID":0,"Divisi":null,"EfekEmiten_EBA":false,"EfekEmiten_ETF":false,"EfekEmiten_Obligasi":true,"EfekEmiten_Saham":true,"EfekEmiten_SPEI":false,"Industri":"Perusahaan Holding & Investasi","SubIndustri":"Perusahaan Holding Keuangan","Email":"corsec.mncfinancialservices@mncgroup.com","Fax":"021-39836886","id":0,"JenisEmiten":null,"KegiatanUsahaUtama":"Investment Company","KodeDivisi":null,"KodeEmiten":"BCAP","NamaEmiten":"MNC Kapital Indonesia Tbk","NPKP":"","NPWP":"01.911.968.4-054.000","PapanPencatatan":"Utama","Sektor":"Keuangan","SubSektor":"Perusahaan Holding & Investasi","TanggalPencatatan":"2001-06-08T00:00:00","Telepon":"021-29709700","Website":"www.mncfinancialservices.com","Status":0,"Logo":"/Portals/0/StaticData/ListedCompanies/LogoEmiten/BCAP.jpg"},{"Alamat":"Menara Bank Danamon, Jl. HR. Rasuna Said, Blok C No 10, Kel. Karet, Kec. Setiabudi, Jakarta Selatan","BAE":"","DataID":0,"Divisi":null,"EfekEmiten_EBA":false,"EfekEmiten_ETF":false,"EfekEmiten_Obligasi":true,"EfekEmiten_Saham":true,"EfekEmiten_SPEI":false,"Industri":"Bank","SubIndustri":"Bank","Email":"corporate.secretary@danamon.co.id","Fax":"(021) 80645033","id":0,"JenisEmiten":null,"KegiatanUsahaUtama":"Jasa Perbankan ","KodeDivisi":null,"KodeEmiten":"BDMN","NamaEmiten":"PT Bank Danamon Indonesia Tbk","NPKP":"01.308.470.2-091.000","NPWP":"01.308.470.2-091.000","PapanPencatatan":"Utama","Sektor":"Keuangan","SubSektor":"Bank","TanggalPencatatan":"1989-12-06T00:00:00","Telepon":"(021) 80645000","Website":"http://www.danamon.co.id/","Status":0,"Logo":"/Portals/0/StaticData/ListedCompanies/LogoEmiten/BDMN.jpg"},{"Alamat":"BFI Tower - Sunburst CBD Lot 1.2, Jl. Kapt. Soebijanto Djojohadikusumo BSD City, Tangerang Selatan, ","BAE":"","DataID":0,"Divisi":null,"EfekEmiten_EBA":false,"EfekEmiten_ETF":false,"EfekEmiten_Obligasi":true,"EfekEmiten_Saham":true,"EfekEmiten_SPEI":false,"Industri":"Pembiayaan Konsumen","SubIndustri":"Pembiayaan Konsumen","Email":"corsec@bfi.co.id ","Fax":"(021) 2966 0757, 2966 58 ","id":0,"JenisEmiten":null,"KegiatanUsahaUtama":"Pembiayaan","KodeDivisi":null,"KodeEmiten":"BFIN","NamaEmiten":"BFI Finance Indonesia Tbk","NPKP":"","NPWP":"01.316.111.2-091.000","PapanPencatatan":"Utama","Sektor":"Keuangan","SubSektor":"Jasa Pembiayaan","TanggalPencatatan":"1990-05-16T00:00:00","Telepon":"(021) 2965 0300, 2965 0500 ","Website":"www.bfi.co.id ","Status":0,"Logo":"/Portals/0/StaticData/ListedCompanies/LogoEmiten/BFIN.jpg"},{"Alamat":"Menara Bank Jabar Banten Jl. Naripan No. 12-14, Bandung 40111, Jawa Barat","BAE":"","DataID":0,"Divisi":null,"EfekEmiten_EBA":false,"EfekEmiten_ETF":false,"EfekEmiten_Obligasi":true,"EfekEmiten_Saham":true,"EfekEmiten_SPEI":false,"Industri":"Bank","SubIndustri":"Bank","Email":"c.trisna@bankjabar.co.id","Fax":"(022) 420 6099","id":0,"JenisEmiten":null,"KegiatanUsahaUtama":"Jasa Perbankan","KodeDivisi":null,"KodeEmiten":"BJBR","NamaEmiten":"Bank Pembangunan Daerah Jawa Barat dan Banten Tbk","NPKP":"","NPWP":"01.118.605.3-441.000","PapanPencatatan":"Utama","Sektor":"Keuangan","SubSektor":"Bank","TanggalPencatatan":"2010-07-08T00:00:00","Telepon":"(022) 423 4868","Website":"www.bankjabarbanten.co.id","Status":0,"Logo":"/Portals/0/StaticData/ListedCompanies/LogoEmiten/BJBR.jpg"},{"Alamat":"Revenue Tower, District 8, SCBD, Jl. Jenderal Sudirman Kav. 52-53, Jakarta 12190","BAE":"","DataID":0,"Divisi":null,"EfekEmiten_EBA":false,"EfekEmiten_ETF":false,"EfekEmiten_Obligasi":true,"EfekEmiten_Saham":true,"EfekEmiten_SPEI":false,"Industri":"Bank","SubIndustri":"Bank","Email":"corporate.communication@qnb.co.id","Fax":"021-5155388","id":0,"JenisEmiten":null,"KegiatanUsahaUtama":"Perbankan/Banking","KodeDivisi":null,"KodeEmiten":"BKSW","NamaEmiten":"PT Bank QNB Indonesia Tbk","NPKP":"","NPWP":"01-100.446.2-054.000","PapanPencatatan":"Pengembangan","Sektor":"Keuangan","SubSektor":"Bank","TanggalPencatatan":"2002-11-21T00:00:00","Telepon":"021-5155155","Website":"qnb.co.id","Status":0,"Logo":"/Portals/0/StaticData/ListedCompanies/LogoEmiten/BKSW.jpg"},{"Alamat":"\tPlaza Mandiri, Jl. Jend. Gatot Subroto Kav.36-38, Jakarta 12190 ","BAE":"","DataID":0,"Divisi":null,"EfekEmiten_EBA":false,"EfekEmiten_ETF":false,"EfekEmiten_Obligasi":true,"EfekEmiten_Saham":true,"EfekEmiten_SPEI":false,"Industri":"Bank","SubIndustri":"Bank","Email":"cma@bankmandiri.co.id","Fax":"\t5274477; 5275577 ","id":0,"JenisEmiten":null,"KegiatanUsahaUtama":"Jasa Keuangan - Perbankan ","KodeDivisi":null,"KodeEmiten":"BMRI","NamaEmiten":"PT Bank Mandiri (Persero) Tbk","NPKP":"0","NPWP":"\t01.061.173.9-093.000 ","PapanPencatatan":"Utama","Sektor":"Keuangan","SubSektor":"Bank","TanggalPencatatan":"2003-07-14T00:00:00","Telepon":"\t5265045; 5265095 (Hunting) ","Website":"\twww.bankmandiri.co.id ","Status":0,"Logo":"/Portals/0/StaticData/ListedCompanies/LogoEmiten/BMRI.jpg"},{"Alamat":"MNC Tower Lantai 27 Suite 2701, Jl. Kebon Sirih No.17-19,  Kebon Sirih, Menteng,  Jakarta Pusat, DKI Jakarta","BAE":"","DataID":0,"Divisi":null,"EfekEmiten_EBA":false,"EfekEmiten_ETF":false,"EfekEmiten_Obligasi":true,"EfekEmiten_Saham":true,"EfekEmiten_SPEI":false,"Industri":"Perusahaan Holding Multi-sektor","SubIndustri":"Perusahaan Holding Multi-sektor","Email":"corsec.mncmedia@mncgroup.com","Fax":"021-3927859","id":0,"JenisEmiten":null,"KegiatanUsahaUtama":"Investment Company","KodeDivisi":null,"KodeEmiten":"BMTR","NamaEmiten":"PT Global Mediacom Tbk","NPKP":"","NPWP":"01.361.257.7-054.000","PapanPencatatan":"Utama","Sektor":"Perindustrian","SubSektor":"Perusahaan Holding Multi Sektor","TanggalPencatatan":"1995-07-17T00:00:00","Telepon":"021-3909211, 021-3900310","Website":"mediacom.co.id","Status":0,"Logo":"/Portals/0/StaticData/ListedCompanies/LogoEmiten/BMTR.jpg"},{"Alamat":"Graha CIMB Niaga\r\nJl. Jend. Sudirman Kav. 58\r\nJakarta 12190","BAE":"","DataID":0,"Divisi":null,"EfekEmiten_EBA":false,"EfekEmiten_ETF":false,"EfekEmiten_Obligasi":true,"EfekEmiten_Saham":true,"EfekEmiten_SPEI":false,"Industri":"Bank","SubIndustri":"Bank","Email":"Corporate.Secretary@cimbniaga.co.id","Fax":"252-6749","id":0,"JenisEmiten":null,"KegiatanUsahaUtama":"Jasa Perbankan ","KodeDivisi":null,"KodeEmiten":"BNGA","NamaEmiten":"PT Bank CIMB Niaga Tbk","NPKP":"KEP-000019/WPJ.19/KP.0103/2008","NPWP":"01.310.668.7-091.000","PapanPencatatan":"Utama","Sektor":"Keuangan","SubSektor":"Bank","TanggalPencatatan":"1989-11-29T00:00:00","Telepon":"250-5252, 250-5353","Website":"www.cimbniaga.com","Status":0,"Logo":"/Portals/0/StaticData/ListedCompanies/LogoEmiten/BNGA.jpg"},{"Alamat":"Sentral Senayan III, 26th floor, Jl. Asia Afrika No. 8, Gelora Bung Karno Senayan, Jakarta 10270","BAE":"","DataID":0,"Divisi":null,"EfekEmiten_EBA":false,"EfekEmiten_ETF":false,"EfekEmiten_Obligasi":true,"EfekEmiten_Saham":true,"EfekEmiten_SPEI":false,"Industri":"Bank","SubIndustri":"Bank","Email":"MRostian@maybank.co.id","Fax":"021-29228730, 021-29228799","id":0,"JenisEmiten":null,"KegiatanUsahaUtama":"Jasa Perbankan","KodeDivisi":null,"KodeEmiten":"BNII","NamaEmiten":"PT Bank Maybank Indonesia Tbk","NPKP":"","NPWP":"01.309.323.2-091.000","PapanPencatatan":"Utama","Sektor":"Keuangan","SubSektor":"Bank","TanggalPencatatan":"1989-11-21T00:00:00","Telepon":"021-29228888","Website":"www.maybank.co.id","Status":0,"Logo":"/Portals/0/StaticData/ListedCompanies/LogoEmiten/BNII.jpg"},{"Alamat":"Gedung World Trade Center II, Jl. Jend. Sudirman Kav. 29-31, Jakarta  12920","BAE":"","DataID":0,"Divisi":null,"EfekEmiten_EBA":false,"EfekEmiten_ETF":false,"EfekEmiten_Obligasi":true,"EfekEmiten_Saham":true,"EfekEmiten_SPEI":false,"Industri":"Bank","SubIndustri":"Bank","Email":"-","Fax":"-","id":0,"JenisEmiten":null,"KegiatanUsahaUtama":"Perbankan","KodeDivisi":null,"KodeEmiten":"BNLI","NamaEmiten":"Bank Permata Tbk","NPKP":"","NPWP":"01.308.464.5-091.000","PapanPencatatan":"Utama","Sektor":"Keuangan","SubSektor":"Bank","TanggalPencatatan":"1990-01-15T00:00:00","Telepon":"021-5237788","Website":"www.permatabank.co.id","Status":0,"Logo":"/Portals/0/StaticData/ListedCompanies/LogoEmiten/BNLI.jpg"},{"Alamat":"CHASE PLAZA LANTAI 16, JL JENDRAL SUDIRMAN KAV.21 JAKARTA","BAE":"","DataID":0,"Divisi":null,"EfekEmiten_EBA":false,"EfekEmiten_ETF":false,"EfekEmiten_Obligasi":true,"EfekEmiten_Saham":true,"EfekEmiten_SPEI":false,"Industri":"Pembiayaan Konsumen","SubIndustri":"Pembiayaan Konsumen","Email":"risma@woorifinance.co.id","Fax":"021-5209160","id":0,"JenisEmiten":null,"KegiatanUsahaUtama":"Jasa Pembiayaan Konsumen","KodeDivisi":null,"KodeEmiten":"BPFI","NamaEmiten":"PT Woori Finance Indonesia Tbk","NPKP":"S-51PKP/WPJ.07/KP.0803/2022","NPWP":"01.710.728.5-054.000","PapanPencatatan":"Pengembangan","Sektor":"Keuangan","SubSektor":"Jasa Pembiayaan","TanggalPencatatan":"2009-06-01T00:00:00","Telepon":"021-5200434","Website":"www.woorifinance.co.id","Status":0,"Logo":"/Portals/0/StaticData/ListedCompanies/LogoEmiten/BPFI.jpg"},{"Alamat":"Gedung The Tower, Jalan Gatot Subroto No.27, Kel. Karet Semanggi, Kec. Setiabudi, Jakarta Selatan 12930","BAE":"PT. Datindo Entrycom","DataID":0,"Divisi":null,"EfekEmiten_EBA":false,"EfekEmiten_ETF":false,"EfekEmiten_Obligasi":true,"EfekEmiten_Saham":true,"EfekEmiten_SPEI":false,"Industri":"Bank","SubIndustri":"Bank","Email":"corporate.secretary@bankbsi.co.id","Fax":"+62 21 30421888","id":0,"JenisEmiten":null,"KegiatanUsahaUtama":"Perbankan Syariah","KodeDivisi":null,"KodeEmiten":"BRIS","NamaEmiten":"PT Bank Syariah Indonesia Tbk","NPKP":"","NPWP":"01.105.094.5-093.000","PapanPencatatan":"Utama","Sektor":"Keuangan","SubSektor":"Bank","TanggalPencatatan":"2018-05-09T00:00:00","Telepon":"+62 21 30405999","Website":"www.bankbsi.co.id","Status":0,"Logo":"/Portals/0/StaticData/ListedCompanies/LogoEmiten/BRIS.jpg"},{"Alamat":"Wisma Barito Pacific Twr. B, LT. 9, JL. Letjen S. Parman Kav.62-63\r\nJakarta","BAE":"","DataID":0,"Divisi":null,"EfekEmiten_EBA":false,"EfekEmiten_ETF":false,"EfekEmiten_Obligasi":true,"EfekEmiten_Saham":true,"EfekEmiten_SPEI":false,"Industri":"Barang Kimia","SubIndustri":"Barang Kimia Dasar","Email":"corpsec@barito.co.id","Fax":"530 6680","id":0,"JenisEmiten":null,"KegiatanUsahaUtama":"Industri, properti, perdagangan, energi terbarukan, kehutanan, perkebunan, pertambangan, transportasi, dan aktivitas perusahaan holding","KodeDivisi":null,"KodeEmiten":"BRPT","NamaEmiten":"Barito Pacific Tbk","NPKP":"","NPWP":"01.124.461.3-054.000","PapanPencatatan":"Utama","Sektor":"Barang Baku","SubSektor":"Barang Baku","TanggalPencatatan":"1993-10-01T00:00:00","Telepon":"(021) 530 6711\r\n","Website":"www.barito-pacific.com","Status":0,"Logo":"/Portals/0/StaticData/ListedCompanies/LogoEmiten/BRPT.jpg"},{"Alamat":"Sinar Mas Land Plaza Wing 3B, BSD Green Office Park, Jl. Grand Boulevard, BSD City Tangerang 15345","BAE":"","DataID":0,"Divisi":null,"EfekEmiten_EBA":false,"EfekEmiten_ETF":false,"EfekEmiten_Obligasi":true,"EfekEmiten_Saham":true,"EfekEmiten_SPEI":false,"Industri":"Pengelola & Pengembang Real Estat","SubIndustri":"Pengembang & Operator Real Estat","Email":"corporate.secretary@sinarmasland.com","Fax":"021-50588270","id":0,"JenisEmiten":null,"KegiatanUsahaUtama":"Property dan Real Estate","KodeDivisi":null,"KodeEmiten":"BSDE","NamaEmiten":"PT Bumi Serpong Damai Tbk","NPKP":"","NPWP":"01.374.249.9-054.000","PapanPencatatan":"Utama","Sektor":"Properti & Real Estat","SubSektor":"Properti & Real Estat","TanggalPencatatan":"2008-06-06T00:00:00","Telepon":"021-50368368","Website":"www.bsdcity.com","Status":0,"Logo":"/Portals/0/StaticData/ListedCompanies/LogoEmiten/BSDE.jpg"},{"Alamat":"Sinar Mas Land Plaza - Menara 1 Lantai 8\r\nl. MH. Thamrin No. 51\r\nJakarta 10350","BAE":"","DataID":0,"Divisi":null,"EfekEmiten_EBA":false,"EfekEmiten_ETF":false,"EfekEmiten_Obligasi":true,"EfekEmiten_Saham":true,"EfekEmiten_SPEI":false,"Industri":"Bank","SubIndustri":"Bank","Email":"retno.t.wulandari@banksinarmas.com","Fax":"021-31990401","id":0,"JenisEmiten":null,"KegiatanUsahaUtama":"Perbankan","KodeDivisi":null,"KodeEmiten":"BSIM","NamaEmiten":"Bank Sinarmas Tbk","NPKP":"-","NPWP":"01.344.613.3-054.000","PapanPencatatan":"Utama","Sektor":"Keuangan","SubSektor":"Bank","TanggalPencatatan":"2010-12-13T00:00:00","Telepon":"021-31990101 ","Website":"www.banksinarmas.com","Status":0,"Logo":"/Portals/0/StaticData/ListedCompanies/LogoEmiten/BSIM.jpg"},{"Alamat":"Menara BTPN, CBD Mega Kuningan Lantai 29, Jl. Dr. Ide Anak Agung Gde Agung Kav. 5.5-5.6 ","BAE":"","DataID":0,"Divisi":null,"EfekEmiten_EBA":false,"EfekEmiten_ETF":false,"EfekEmiten_Obligasi":true,"EfekEmiten_Saham":true,"EfekEmiten_SPEI":false,"Industri":"Bank","SubIndustri":"Bank","Email":"corporate.secretary@btpn.com ","Fax":" 021-300 26 309  ","id":0,"JenisEmiten":null,"KegiatanUsahaUtama":"Perbankan","KodeDivisi":null,"KodeEmiten":"BTPN","NamaEmiten":"PT Bank BTPN Tbk","NPKP":"","NPWP":"01.139.797.3-091.000","PapanPencatatan":"Utama","Sektor":"Keuangan","SubSektor":"Bank","TanggalPencatatan":"2008-03-12T00:00:00","Telepon":" 021-300 26 200  ","Website":"www.btpn.com ","Status":0,"Logo":"/Portals/0/StaticData/ListedCompanies/LogoEmiten/BTPN.jpg"},{"Alamat":"Graha BIP Lantai 10, Jl. Gatot Subroto Kav. 23, Jakarta","BAE":"","DataID":0,"Divisi":null,"EfekEmiten_EBA":false,"EfekEmiten_ETF":false,"EfekEmiten_Obligasi":true,"EfekEmiten_Saham":true,"EfekEmiten_SPEI":false,"Industri":"Bank","SubIndustri":"Bank","Email":"corsec@victoriabank.co.id","Fax":"021-5228777","id":0,"JenisEmiten":null,"KegiatanUsahaUtama":"Perbankan","KodeDivisi":null,"KodeEmiten":"BVIC","NamaEmiten":"Bank Victoria International Tbk","NPKP":"-","NPWP":"01.592.025.9-054.000","PapanPencatatan":"Utama","Sektor":"Keuangan","SubSektor":"Bank","TanggalPencatatan":"1999-06-30T00:00:00","Telepon":"021-5228888","Website":"www.victoriabank.co.id","Status":0,"Logo":"/Portals/0/StaticData/ListedCompanies/LogoEmiten/BVIC.jpg"},{"Alamat":"Sinarmas MSIG Tower, Lantai 9, Jl. Jendral Sudirman Kav.21, Setiabudi, Karet, Jakarta Selatan","BAE":"PT. Sinartama Gunita","DataID":0,"Divisi":null,"EfekEmiten_EBA":false,"EfekEmiten_ETF":false,"EfekEmiten_Obligasi":true,"EfekEmiten_Saham":true,"EfekEmiten_SPEI":false,"Industri":"Batu Bara","SubIndustri":"Distribusi Batu Bara","Email":"wim.andrian@energigroupindonesia.com","Fax":"021-80511134","id":0,"JenisEmiten":null,"KegiatanUsahaUtama":"Penambangan Batubara","KodeDivisi":null,"KodeEmiten":"CNKO","NamaEmiten":"Exploitasi Energi Indonesia Tbk","NPKP":"","NPWP":"01.901.192.3-054.000","PapanPencatatan":"Pengembangan","Sektor":"Energi","SubSektor":"Minyak, Gas & Batu Bara","TanggalPencatatan":"2001-11-20T00:00:00","Telepon":"021-80511130\r\n021-80511131\r\n021-80511132\r\n021-80511133","Website":"www.energigroupindonesia.com","Status":0,"Logo":"/Portals/0/StaticData/ListedCompanies/LogoEmiten/CNKO.jpg"},{"Alamat":"Chase Plaza Tower Lt. 21\r\nJl. Jend. Sudirman Kav. 21\r\nJakarta","BAE":"","DataID":0,"Divisi":null,"EfekEmiten_EBA":false,"EfekEmiten_ETF":false,"EfekEmiten_Obligasi":true,"EfekEmiten_Saham":true,"EfekEmiten_SPEI":false,"Industri":"Pengelola & Pengembang Real Estat","SubIndustri":"Pengembang & Operator Real Estat","Email":"Greg@dutaanggada.com","Fax":"520-8300","id":0,"JenisEmiten":null,"KegiatanUsahaUtama":"Property dan Real Estate","KodeDivisi":null,"KodeEmiten":"DART","NamaEmiten":"Duta Anggada Realty Tbk","NPKP":"","NPWP":"01.366.015.4-054.000","PapanPencatatan":"Utama","Sektor":"Properti & Real Estat","SubSektor":"Properti & Real Estat","TanggalPencatatan":"1990-05-08T00:00:00","Telepon":"520-8000","Website":"0","Status":0,"Logo":"/Portals/0/StaticData/ListedCompanies/LogoEmiten/DART.jpg"},{"Alamat":"Intiland Tower, Penthouse floor, Jl. Jend. Sudirman 32, Jakarta 10220, Indonesia","BAE":"","DataID":0,"Divisi":null,"EfekEmiten_EBA":false,"EfekEmiten_ETF":false,"EfekEmiten_Obligasi":true,"EfekEmiten_Saham":true,"EfekEmiten_SPEI":false,"Industri":"Pengelola & Pengembang Real Estat","SubIndustri":"Pengembang & Operator Real Estat","Email":"info@intiland.com","Fax":"+62 21 570 0015","id":0,"JenisEmiten":null,"KegiatanUsahaUtama":"Property dan Real Estate","KodeDivisi":null,"KodeEmiten":"DILD","NamaEmiten":"Intiland Development Tbk","NPKP":"","NPWP":"01.060.126.8-054.000","PapanPencatatan":"Utama","Sektor":"Properti & Real Estat","SubSektor":"Properti & Real Estat","TanggalPencatatan":"1991-09-04T00:00:00","Telepon":"+62 21 570 1912, 570 8088","Website":"www.intiland.com","Status":0,"Logo":"/Portals/0/StaticData/ListedCompanies/LogoEmiten/DILD.jpg"},{"Alamat":"Sapta Mulia Center, Jl. Rawa Gelam V Kav OR/3B, Kawasan Industri Pulo Gadung, Jakarta 13930","BAE":"","DataID":0,"Divisi":null,"EfekEmiten_EBA":false,"EfekEmiten_ETF":false,"EfekEmiten_Obligasi":true,"EfekEmiten_Saham":true,"EfekEmiten_SPEI":false,"Industri":"Produk Makanan Pertanian","SubIndustri":"Perkebunan & Tanaman Pangan","Email":"info@dsngroup.co.id","Fax":"(+62) 21 4606942","id":0,"JenisEmiten":null,"KegiatanUsahaUtama":"Industri Pengolahan Kelapa Sawit, Industri Pengolahan Kayu, Perkebunan dan Hutan Tanaman Industri melalui Perseroan dan Entitas Anak","KodeDivisi":null,"KodeEmiten":"DSNG","NamaEmiten":"PT Dharma Satya Nusantara Tbk.","NPKP":"-","NPWP":"01.060.268.8-054.000","PapanPencatatan":"Utama","Sektor":"Barang Konsumen Primer","SubSektor":"Makanan & Minuman","TanggalPencatatan":"2013-06-14T00:00:00","Telepon":"(+62) 21 4618135","Website":"www.dsn.co.id","Status":0,"Logo":"/Portals/0/StaticData/ListedCompanies/LogoEmiten/DSNG.jpg"},{"Alamat":"Business Park Kebon Jeruk Blok C.2 No. 1\r\nJalan Meruya Ilir No. 88, Kelurahan Meruya Utara\r\nKecamatan Kembangan, Jakarta Barat","BAE":"PT. Datindo Entrycom","DataID":0,"Divisi":null,"EfekEmiten_EBA":false,"EfekEmiten_ETF":false,"EfekEmiten_Obligasi":true,"EfekEmiten_Saham":true,"EfekEmiten_SPEI":false,"Industri":"Pariwisata & Rekreasi","SubIndustri":"Rumah Makan","Email":"duckkingjbi@theduckking.com","Fax":"+62 21 30067858","id":0,"JenisEmiten":null,"KegiatanUsahaUtama":"Bidang perdagangan, industri dan jasa","KodeDivisi":null,"KodeEmiten":"DUCK","NamaEmiten":"PT Jaya Bersama Indo Tbk.","NPKP":"","NPWP":"31.721.836.0-086.000","PapanPencatatan":"Pengembangan","Sektor":"Barang Konsumen Non-Primer","SubSektor":"Jasa Konsumen","TanggalPencatatan":"2018-10-10T00:00:00","Telepon":"+62 21 58901634","Website":"jbi.reqcode.com","Status":0,"Logo":"/Portals/0/StaticData/ListedCompanies/LogoEmiten/DUCK.jpg"},{"Alamat":"Graha Elnusa, Jl. TB Simatupang Kav. 1B, Jakarta 12560","BAE":"","DataID":0,"Divisi":null,"EfekEmiten_EBA":false,"EfekEmiten_ETF":false,"EfekEmiten_Obligasi":true,"EfekEmiten_Saham":true,"EfekEmiten_SPEI":false,"Industri":"Pendukung Minyak, Gas & Batu Bara","SubIndustri":"Jasa Pengeboran Minyak & Gas","Email":"corporate@elnusa.co.id","Fax":"(021) 788-30883","id":0,"JenisEmiten":null,"KegiatanUsahaUtama":"Jasa Energi","KodeDivisi":null,"KodeEmiten":"ELSA","NamaEmiten":"Elnusa Tbk","NPKP":"","NPWP":"01.000.050.3-051.000","PapanPencatatan":"Utama","Sektor":"Energi","SubSektor":"Minyak, Gas & Batu Bara","TanggalPencatatan":"2008-02-06T00:00:00","Telepon":"(021) 788-30850","Website":"www.elnusa.co.id","Status":0,"Logo":"/Portals/0/StaticData/ListedCompanies/LogoEmiten/ELSA.jpg"},{"Alamat":"Gedung XL Axiata Tower Jl. HR Rasuna Said Kav 11-12 Blok X-5 RT.007 RW 002 Kuningan Timur Setiabudi Jakarta Selatan DKI Jakarta 12950","BAE":"","DataID":0,"Divisi":null,"EfekEmiten_EBA":false,"EfekEmiten_ETF":false,"EfekEmiten_Obligasi":true,"EfekEmiten_Saham":true,"EfekEmiten_SPEI":false,"Industri":"Jasa Telekomunikasi Nirkabel","SubIndustri":"Jasa Telekomunikasi Nirkabel","Email":"Corpsec@xl.co.id","Fax":"(021) 576 1880","id":0,"JenisEmiten":null,"KegiatanUsahaUtama":"Penyelenggaraan Jasa Telekomunikasi dan/atau Jaringan Telekomunikasi dan/atau Multimedia","KodeDivisi":null,"KodeEmiten":"EXCL","NamaEmiten":"PT XL Axiata Tbk","NPKP":"-","NPWP":"01.345.276.8-092.000","PapanPencatatan":"Utama","Sektor":"Infrastruktur","SubSektor":"Telekomunikasi","TanggalPencatatan":"2005-09-29T00:00:00","Telepon":"(021) 576 1881","Website":"www.xl.co.id","Status":0,"Logo":"/Portals/0/StaticData/ListedCompanies/LogoEmiten/EXCL.jpg"},{"Alamat":"Jl. Jend. MT.Haryono Kav.7, Tebet Barat Tebet","BAE":"","DataID":0,"Divisi":null,"EfekEmiten_EBA":false,"EfekEmiten_ETF":false,"EfekEmiten_Obligasi":true,"EfekEmiten_Saham":true,"EfekEmiten_SPEI":false,"Industri":"Pariwisata & Rekreasi","SubIndustri":"Rumah Makan","Email":"jd.juwono@kfcindonesia.com","Fax":"298387, 8300569","id":0,"JenisEmiten":null,"KegiatanUsahaUtama":"Food and Beverages","KodeDivisi":null,"KodeEmiten":"FAST","NamaEmiten":"PT Fast Food Indonesia Tbk","NPKP":"0","NPWP":"01.306.783.0-092.000","PapanPencatatan":"Pengembangan","Sektor":"Barang Konsumen Non-Primer","SubSektor":"Jasa Konsumen","TanggalPencatatan":"1993-05-11T00:00:00","Telepon":"8310919, 8298390, 8309382, 8309383","Website":"http://www.kfcindonesia.com","Status":0,"Logo":"/Portals/0/StaticData/ListedCompanies/LogoEmiten/FAST.jpg"},{"Alamat":"Wisma 77, Tower 1, Lt. 8\r\nJln. Jend. S. Parman Kav. 77, Jakarta Barat, 11410","BAE":"PT. Adimitra Jasa Korpora","DataID":0,"Divisi":null,"EfekEmiten_EBA":false,"EfekEmiten_ETF":false,"EfekEmiten_Obligasi":true,"EfekEmiten_Saham":true,"EfekEmiten_SPEI":false,"Industri":"Pengelola & Pengembang Real Estat","SubIndustri":"Pengembang & Operator Real Estat","Email":"corporate@forzaland.com","Fax":"(021) 5366 1752","id":0,"JenisEmiten":null,"KegiatanUsahaUtama":"Pembangunan, pengelolaan dan perdagangan real estate/properti.","KodeDivisi":null,"KodeEmiten":"FORZ","NamaEmiten":"PT Forza Land Indonesia Tbk.","NPKP":"PEM-02921/WPJ.06/KP.1603/2012","NPWP":"03.219.966.3-077.000","PapanPencatatan":"Pengembangan","Sektor":"Properti & Real Estat","SubSektor":"Properti & Real Estat","TanggalPencatatan":"2017-04-28T00:00:00","Telepon":"(021) 5366 9777","Website":"www.forzaland.com","Status":0,"Logo":"/Portals/0/StaticData/ListedCompanies/LogoEmiten/FORZ.jpg"},{"Alamat":"TCC Batavia Tower One Lantai 35, Jl. K.H. Mas Mansyur Kav. 126,Jakarta Pusat 10220","BAE":"PT. Adimitra Jasa Korpora","DataID":0,"Divisi":null,"EfekEmiten_EBA":false,"EfekEmiten_ETF":false,"EfekEmiten_Obligasi":true,"EfekEmiten_Saham":true,"EfekEmiten_SPEI":false,"Industri":"Pengelola & Pengembang Real Estat","SubIndustri":"Pengembang & Operator Real Estat","Email":"pr@greenwoodsejahtera.com","Fax":"2598-4578","id":0,"JenisEmiten":null,"KegiatanUsahaUtama":"Pembangunan dan pengembangan, investasi, perdagangan, dan jasa penyewaan properti","KodeDivisi":null,"KodeEmiten":"GWSA","NamaEmiten":"PT Greenwood Sejahtera Tbk","NPKP":"-","NPWP":"01.568.937.5-054.000","PapanPencatatan":"Utama","Sektor":"Properti & Real Estat","SubSektor":"Properti & Real Estat","TanggalPencatatan":"2011-12-23T00:00:00","Telepon":"2598-4969","Website":"http://www.greenwoodsejahtera.com","Status":0,"Logo":"/Portals/0/StaticData/ListedCompanies/LogoEmiten/GWSA.jpg"},{"Alamat":"Jalan Raya Jatinegara Barat No. 126\r\nJakarta Timur 13320","BAE":"","DataID":0,"Divisi":null,"EfekEmiten_EBA":false,"EfekEmiten_ETF":false,"EfekEmiten_Obligasi":true,"EfekEmiten_Saham":true,"EfekEmiten_SPEI":false,"Industri":"Penyedia Jasa Kesehatan","SubIndustri":"Penyedia Jasa Kesehatan","Email":"corporate.secretary@herminahospitals.com","Fax":"021 - 8560601","id":0,"JenisEmiten":null,"KegiatanUsahaUtama":"Aktivitas Rumah Sakit Swasta","KodeDivisi":null,"KodeEmiten":"HEAL","NamaEmiten":"PT Medikaloka Hermina Tbk.","NPKP":"","NPWP":"01.920.115.1-007.000","PapanPencatatan":"Utama","Sektor":"Kesehatan","SubSektor":"Jasa & Peralatan Kesehatan","TanggalPencatatan":"2018-05-16T00:00:00","Telepon":"021 - 8572525","Website":"www.herminahospitals.com","Status":0,"Logo":"/Portals/0/StaticData/ListedCompanies/LogoEmiten/HEAL.jpg"},{"Alamat":"Jl. Kopo Sayati No. 163-165 \r\nKabupaten Bandung, Jawa Barat\r\n","BAE":"","DataID":0,"Divisi":null,"EfekEmiten_EBA":false,"EfekEmiten_ETF":false,"EfekEmiten_Obligasi":true,"EfekEmiten_Saham":true,"EfekEmiten_SPEI":false,"Industri":"Pakaian & Barang Mewah","SubIndustri":"Pakaian, Aksesoris, & Tas","Email":"corsec@hartadinataabadi.co.id","Fax":"+62 22 5403002","id":0,"JenisEmiten":null,"KegiatanUsahaUtama":"Perindustrian dan Perdagangan","KodeDivisi":null,"KodeEmiten":"HRTA","NamaEmiten":"PT Hartadinata Abadi Tbk","NPKP":"","NPWP":"02.267.114.3-445.000","PapanPencatatan":"Utama","Sektor":"Barang Konsumen Non-Primer","SubSektor":"Pakaian & Barang Mewah","TanggalPencatatan":"2017-06-21T00:00:00","Telepon":"+62 22 5402326","Website":"www.hartadinata.com","Status":0,"Logo":"/Portals/0/StaticData/ListedCompanies/LogoEmiten/HRTA.jpg"},{"Alamat":"Altira Office Tower Lantai 38, Altira Business Park, JL Yos Sudarso No. 85  \r\nJakarta Utara14350","BAE":"","DataID":0,"Divisi":null,"EfekEmiten_EBA":false,"EfekEmiten_ETF":false,"EfekEmiten_Obligasi":true,"EfekEmiten_Saham":true,"EfekEmiten_SPEI":false,"Industri":"Produk & Perlengkapan Bangunan","SubIndustri":"Produk & Perlengkapan Bangunan","Email":"corporate.secretary@impack-pratama.com","Fax":"6221-65311041","id":0,"JenisEmiten":null,"KegiatanUsahaUtama":"Produsen dan distributor bahan bangunan dan barang plastik ","KodeDivisi":null,"KodeEmiten":"IMPC","NamaEmiten":"PT Impack Pratama Industri Tbk","NPKP":"","NPWP":"01.361.563.8-046.000","PapanPencatatan":"Pengembangan","Sektor":"Perindustrian","SubSektor":"Barang Perindustrian","TanggalPencatatan":"2014-12-17T00:00:00","Telepon":"6221- 65311045","Website":"www.impack-pratama.com","Status":0,"Logo":"/Portals/0/StaticData/ListedCompanies/LogoEmiten/IMPC.jpg"},{"Alamat":"Sudirman Plaza, Indofood Tower, Lt. 27, Jl. Jend. Sudirman Kav. 76-78 Jakarta 12910","BAE":"","DataID":0,"Divisi":null,"EfekEmiten_EBA":false,"EfekEmiten_ETF":false,"EfekEmiten_Obligasi":true,"EfekEmiten_Saham":true,"EfekEmiten_SPEI":false,"Industri":"Makanan Olahan","SubIndustri":"Makanan Olahan","Email":"corporate.secretary@indofood.co.id","Fax":"6221 5793 5960","id":0,"JenisEmiten":null,"KegiatanUsahaUtama":"Food and Beverages","KodeDivisi":null,"KodeEmiten":"INDF","NamaEmiten":"Indofood Sukses Makmur Tbk","NPKP":"-","NPWP":"01.542.658.8-092.000","PapanPencatatan":"Utama","Sektor":"Barang Konsumen Primer","SubSektor":"Makanan & Minuman","TanggalPencatatan":"1994-07-14T00:00:00","Telepon":"6221 5795 8822","Website":"www.indofood.com","Status":0,"Logo":"/Portals/0/StaticData/ListedCompanies/LogoEmiten/INDF.jpg"},{"Alamat":"GEDUNG SINAR MAS LAND PLAZA MENARA 2 LT 9 JL MH.THAMRIN NO 51 GONDANGDIA MENTENG JAKARTA PUSAT DKI JAKARTA 10350","BAE":"","DataID":0,"Divisi":null,"EfekEmiten_EBA":false,"EfekEmiten_ETF":false,"EfekEmiten_Obligasi":true,"EfekEmiten_Saham":true,"EfekEmiten_SPEI":false,"Industri":"Perhutanan & Kertas","SubIndustri":"Kertas","Email":"yan_partawijaya@app.co.id; suhendra_wiriadinata@app.co.id; heri_santoso@app.co.id; lydia_lydia@app.co.id","Fax":"021 - 3927685","id":0,"JenisEmiten":null,"KegiatanUsahaUtama":"Pulp and Paper","KodeDivisi":null,"KodeEmiten":"INKP","NamaEmiten":"Indah Kiat Pulp & Paper Tbk","NPKP":"-","NPWP":"01.000.566.8-092.000","PapanPencatatan":"Utama","Sektor":"Barang Baku","SubSektor":"Barang Baku","TanggalPencatatan":"1990-07-16T00:00:00","Telepon":"021-29650800","Website":"www.asiapulppaper.com","Status":0,"Logo":"/Portals/0/StaticData/ListedCompanies/LogoEmiten/INKP.jpg"},{"Alamat":" Jl. Medan Merdeka Barat No.21 Jakarta 10110","BAE":"","DataID":0,"Divisi":null,"EfekEmiten_EBA":false,"EfekEmiten_ETF":false,"EfekEmiten_Obligasi":true,"EfekEmiten_Saham":true,"EfekEmiten_SPEI":false,"Industri":"Jasa Telekomunikasi Nirkabel","SubIndustri":"Jasa Telekomunikasi Nirkabel","Email":"investor@indosatooredoo.com","Fax":"(021) 3000 3757","id":0,"JenisEmiten":null,"KegiatanUsahaUtama":"Telekomunikasi","KodeDivisi":null,"KodeEmiten":"ISAT","NamaEmiten":"PT Indosat Tbk","NPKP":"","NPWP":"01.000.502.3-051.000","PapanPencatatan":"Utama","Sektor":"Infrastruktur","SubSektor":"Telekomunikasi","TanggalPencatatan":"1994-10-19T00:00:00","Telepon":"(021) 3000 3001","Website":"indosatooredoo.com","Status":0,"Logo":"/Portals/0/StaticData/ListedCompanies/LogoEmiten/ISAT.jpg"},{"Alamat":"Jl. Kalibutuh 189-191 Surabaya 60173-Jawa Timur ","BAE":"","DataID":0,"Divisi":null,"EfekEmiten_EBA":false,"EfekEmiten_ETF":false,"EfekEmiten_Obligasi":true,"EfekEmiten_Saham":true,"EfekEmiten_SPEI":false,"Industri":"Logam & Mineral","SubIndustri":"Baja & Besi","Email":"corsec@spindo.co.id","Fax":"(031) 5310712, 5320290 ","id":0,"JenisEmiten":null,"KegiatanUsahaUtama":"Industri pipa baja","KodeDivisi":null,"KodeEmiten":"ISSP","NamaEmiten":"PT Steel Pipe Industry of Indonesia Tbk","NPKP":"","NPWP":"01.001.732.5-092.000 ","PapanPencatatan":"Utama","Sektor":"Barang Baku","SubSektor":"Barang Baku","TanggalPencatatan":"2013-02-22T00:00:00","Telepon":"(031) 5320921, 5316921 ","Website":"www.spindo.com ","Status":0,"Logo":"/Portals/0/StaticData/ListedCompanies/LogoEmiten/ISSP.jpg"},{"Alamat":"Wisma Millenia Lt. 7 Jl. MT Haryono Kav. 16 Jakarta 12810","BAE":"","DataID":0,"Divisi":null,"EfekEmiten_EBA":false,"EfekEmiten_ETF":false,"EfekEmiten_Obligasi":true,"EfekEmiten_Saham":true,"EfekEmiten_SPEI":false,"Industri":"Produk Makanan Pertanian","SubIndustri":"Ikan, Daging & Produk Unggas","Email":"maya.pradjono@japfa.com; yakobus.sugeng@japfa.com; corsec@japfa.com","Fax":"021-8310309","id":0,"JenisEmiten":null,"KegiatanUsahaUtama":"Animal Feed","KodeDivisi":null,"KodeEmiten":"JPFA","NamaEmiten":"JAPFA Comfeed Indonesia Tbk","NPKP":"-","NPWP":"01.002.845.4-092.000","PapanPencatatan":"Utama","Sektor":"Barang Konsumen Primer","SubSektor":"Makanan & Minuman","TanggalPencatatan":"1989-10-23T00:00:00","Telepon":"021-28545680","Website":"http://www.japfacomfeed.co.id","Status":0,"Logo":"/Portals/0/StaticData/ListedCompanies/LogoEmiten/JPFA.jpg"},{"Alamat":"Plaza Tol Taman Mini Indonesia Indah Jakarta 13550","BAE":"","DataID":0,"Divisi":null,"EfekEmiten_EBA":false,"EfekEmiten_ETF":false,"EfekEmiten_Obligasi":true,"EfekEmiten_Saham":true,"EfekEmiten_SPEI":false,"Industri":"Operator Infrastruktur Transportasi","SubIndustri":"Operator Jalan Tol & Rel","Email":"investor.relations@jasamarga.co.id","Fax":"021-8413540","id":0,"JenisEmiten":null,"KegiatanUsahaUtama":"Pengusahaan Jasa Jalan Tol","KodeDivisi":null,"KodeEmiten":"JSMR","NamaEmiten":"PT Jasa Marga Tbk","NPKP":"","NPWP":"01.001.675.6-093.000","PapanPencatatan":"Utama","Sektor":"Infrastruktur","SubSektor":"Infrastruktur Transportasi","TanggalPencatatan":"2007-11-12T00:00:00","Telepon":"021-8413630; 021-8413526","Website":"www.jasamarga.com","Status":0,"Logo":"/Portals/0/StaticData/ListedCompanies/LogoEmiten/JSMR.jpg"},{"Alamat":"Gedung Meta Epsi Lantai 2\r\nJl. Mayjend D.I. Panjaitan Kav. 2, Jakarta Timur","BAE":"PT. Datindo Entrycom","DataID":0,"Divisi":null,"EfekEmiten_EBA":false,"EfekEmiten_ETF":false,"EfekEmiten_Obligasi":true,"EfekEmiten_Saham":true,"EfekEmiten_SPEI":false,"Industri":"Jasa Telekomunikasi","SubIndustri":"Jasa Telekomunikasi Kabel","Email":" hq@triasmitra.com","Fax":"(021) 22085151","id":0,"JenisEmiten":null,"KegiatanUsahaUtama":"Pembangunan, penjualan dan pemeliharaan jaringan telekomunikasi kabel serat optik","KodeDivisi":null,"KodeEmiten":"KETR","NamaEmiten":"PT Ketrosden Triasmitra Tbk","NPKP":"","NPWP":"01.674.225.6-015.000","PapanPencatatan":"Utama","Sektor":"Infrastruktur","SubSektor":"Telekomunikasi","TanggalPencatatan":"2021-01-11T00:00:00","Telepon":"(021) 22085100","Website":"www.triasmitra.com","Status":0,"Logo":"/Portals/0/StaticData/ListedCompanies/LogoEmiten/KETR.jpg"},{"Alamat":"Graha Corner Stone \r\nJl. Rajawali Selatan II No. 1, Kemayoran,\r\nJakarta Pusat 10720\r\n","BAE":"PT. Raya Saham Registra","DataID":0,"Divisi":null,"EfekEmiten_EBA":false,"EfekEmiten_ETF":false,"EfekEmiten_Obligasi":true,"EfekEmiten_Saham":true,"EfekEmiten_SPEI":false,"Industri":"Mesin","SubIndustri":"Mesin Konstruksi & Kendaraan Berat","Email":"0","Fax":"(021) 64713220","id":0,"JenisEmiten":null,"KegiatanUsahaUtama":"Industri kapal laut","KodeDivisi":null,"KodeEmiten":"KPAL","NamaEmiten":"PT Steadfast Marine Tbk","NPKP":"","NPWP":"02.435.621.4-026.000","PapanPencatatan":"Pengembangan","Sektor":"Perindustrian","SubSektor":"Barang Perindustrian","TanggalPencatatan":"2018-06-08T00:00:00","Telepon":"(021) 64713088","Website":"www.steadfast-marine.com","Status":0,"Logo":"/Portals/0/StaticData/ListedCompanies/LogoEmiten/KPAL.jpg"},{"Alamat":"Graha Indramas, JL AIP II KS Tubun Raya No.77 Jakarta 11410","BAE":"","DataID":0,"Divisi":null,"EfekEmiten_EBA":false,"EfekEmiten_ETF":false,"EfekEmiten_Obligasi":true,"EfekEmiten_Saham":true,"EfekEmiten_SPEI":false,"Industri":"Barang Kimia","SubIndustri":"Barang Kimia Dasar","Email":"herman.santoso@lautan-luas.com","Fax":"-","id":0,"JenisEmiten":null,"KegiatanUsahaUtama":"Distribusi Bahan Kimia","KodeDivisi":null,"KodeEmiten":"LTLS","NamaEmiten":"PT Lautan Luas Tbk","NPKP":"-","NPWP":"01.315.900.9-054.000","PapanPencatatan":"Utama","Sektor":"Barang Baku","SubSektor":"Barang Baku","TanggalPencatatan":"1997-07-21T00:00:00","Telepon":"(021) 80660777","Website":"www.lautan-luas.com","Status":0,"Logo":"/Portals/0/StaticData/ListedCompanies/LogoEmiten/LTLS.jpg"},{"Alamat":"Gedung Sahid Sudirman Center lt. 29 Jl. Jend. Sudirman kav. 86 Karet Tengsin Tanah Abang Jakarta Pusat DKI Jakarta ","BAE":"PT. Datindo Entrycom","DataID":0,"Divisi":null,"EfekEmiten_EBA":false,"EfekEmiten_ETF":false,"EfekEmiten_Obligasi":true,"EfekEmiten_Saham":true,"EfekEmiten_SPEI":false,"Industri":"Ritel Khusus","SubIndustri":"Ritel Pakaian & Tekstil","Email":"corporate.secretary@map.co.id","Fax":"+62-21 574 6786","id":0,"JenisEmiten":null,"KegiatanUsahaUtama":"Perdagangan Umum, ritel, kafe restoran","KodeDivisi":null,"KodeEmiten":"MAPI","NamaEmiten":"Mitra Adiperkasa Tbk","NPKP":"0","NPWP":"01.710.880.4-054.000","PapanPencatatan":"Utama","Sektor":"Barang Konsumen Non-Primer","SubSektor":"Perdagangan Ritel","TanggalPencatatan":"2004-11-10T00:00:00","Telepon":"+62-21 8064 8498","Website":"www.map.co.id","Status":0,"Logo":"/Portals/0/StaticData/ListedCompanies/LogoEmiten/MAPI.jpg"},{"Alamat":"Mayapada Tower Lt. 1\r\nJl. Jend. Sudirman Kav. 28\r\nJakarta","BAE":"","DataID":0,"Divisi":null,"EfekEmiten_EBA":false,"EfekEmiten_ETF":false,"EfekEmiten_Obligasi":true,"EfekEmiten_Saham":true,"EfekEmiten_SPEI":false,"Industri":"Bank","SubIndustri":"Bank","Email":"corsec@bankmayapada.com","Fax":"021-57940100","id":0,"JenisEmiten":null,"KegiatanUsahaUtama":"Perbankan","KodeDivisi":null,"KodeEmiten":"MAYA","NamaEmiten":"PT Bank Mayapada Internasional Tbk","NPKP":"","NPWP":"01.590.695.1-091.000","PapanPencatatan":"Utama","Sektor":"Keuangan","SubSektor":"Bank","TanggalPencatatan":"1997-08-29T00:00:00","Telepon":"021-5212288","Website":"www.bankmayapada.com","Status":0,"Logo":"/Portals/0/StaticData/ListedCompanies/LogoEmiten/MAYA.jpg"},{"Alamat":"Treasury Tower, lantai 67, District 8 SCBD Lot. 28 Jl. Jend. Sudirman Kav. 52-53, Jakarta Selatan 12910","BAE":"","DataID":0,"Divisi":null,"EfekEmiten_EBA":false,"EfekEmiten_ETF":false,"EfekEmiten_Obligasi":true,"EfekEmiten_Saham":true,"EfekEmiten_SPEI":false,"Industri":"Logam & Mineral","SubIndustri":"Emas","Email":"corporate.secretary@merdekacoppergold.com","Fax":"021 3952 5589","id":0,"JenisEmiten":null,"KegiatanUsahaUtama":"Pertambangan emas, perak, tembaga, nikel, dan mineral ikutan lainnya, industri dan kegiatan usaha terkait lainnya melalui perusahaan anak Perseroan","KodeDivisi":null,"KodeEmiten":"MDKA","NamaEmiten":"PT Merdeka Copper Gold Tbk.","NPKP":"S-57PKP/WPJ.07/KP.0803/2022","NPWP":"03.272.012.0-011.000","PapanPencatatan":"Utama","Sektor":"Barang Baku","SubSektor":"Barang Baku","TanggalPencatatan":"2015-06-19T00:00:00","Telepon":"021 3952 5580","Website":"www.merdekacoppergold.com","Status":0,"Logo":"/Portals/0/StaticData/ListedCompanies/LogoEmiten/MDKA.jpg"},{"Alamat":"Green Central City, Commercial Area 5th Floor\r\nJl. Gajah Mada No. 188\r\nJakarta Barat 11120","BAE":"","DataID":0,"Divisi":null,"EfekEmiten_EBA":false,"EfekEmiten_ETF":false,"EfekEmiten_Obligasi":true,"EfekEmiten_Saham":true,"EfekEmiten_SPEI":false,"Industri":"Pengelola & Pengembang Real Estat","SubIndustri":"Pengembang & Operator Real Estat","Email":"corporate@modernland.co.id","Fax":"021 - 29369999","id":0,"JenisEmiten":null,"KegiatanUsahaUtama":"Property dan Real Estate","KodeDivisi":null,"KodeEmiten":"MDLN","NamaEmiten":"PT Modernland Realty Tbk.","NPKP":"","NPWP":"01.369.416.1-054.000","PapanPencatatan":"Utama","Sektor":"Properti & Real Estat","SubSektor":"Properti & Real Estat","TanggalPencatatan":"1993-01-18T00:00:00","Telepon":"021 - 29365888","Website":"0","Status":0,"Logo":"/Portals/0/StaticData/ListedCompanies/LogoEmiten/MDLN.jpg"},{"Alamat":"Gedung The Energy, Lantai 52 SCBD Lot, 11A, Jl. Jend. Sudirman Kav. 52-53, Senayan, Kebayoran Baru, Jakarta Selatan","BAE":"","DataID":0,"Divisi":null,"EfekEmiten_EBA":false,"EfekEmiten_ETF":false,"EfekEmiten_Obligasi":true,"EfekEmiten_Saham":true,"EfekEmiten_SPEI":false,"Industri":"Minyak & Gas","SubIndustri":"Produksi & Penyulingan Minyak & Gas","Email":"corporate.secretary@medcoenergi.com","Fax":"(021) 2995-3001","id":0,"JenisEmiten":null,"KegiatanUsahaUtama":"Crude Petroleum and Natural Gas Prod.","KodeDivisi":null,"KodeEmiten":"MEDC","NamaEmiten":"PT Medco Energi Internasional Tbk","NPKP":"","NPWP":"\t01.002.095.6-081.000","PapanPencatatan":"Utama","Sektor":"Energi","SubSektor":"Minyak, Gas & Batu Bara","TanggalPencatatan":"1994-10-12T00:00:00","Telepon":"(021) 2995-3000","Website":"www.medcoenergi.com ","Status":0,"Logo":"/Portals/0/StaticData/ListedCompanies/LogoEmiten/MEDC.jpg"},{"Alamat":"Jl. Menteng Raya No. 24 A-B, Jakarta Pusat 10340\r\n","BAE":"","DataID":0,"Divisi":null,"EfekEmiten_EBA":false,"EfekEmiten_ETF":false,"EfekEmiten_Obligasi":true,"EfekEmiten_Saham":true,"EfekEmiten_SPEI":false,"Industri":"Pembiayaan Konsumen","SubIndustri":"Pembiayaan Konsumen","Email":"corsec@mandalafinance.com","Fax":"021-29259950","id":0,"JenisEmiten":null,"KegiatanUsahaUtama":"Pembiayaan","KodeDivisi":null,"KodeEmiten":"MFIN","NamaEmiten":"PT Mandala Multifinance Tbk.","NPKP":"","NPWP":"01.365.313.4-054.000","PapanPencatatan":"Pengembangan","Sektor":"Keuangan","SubSektor":"Jasa Pembiayaan","TanggalPencatatan":"2005-09-06T00:00:00","Telepon":"021-29259955","Website":"www.mandalafinance.com","Status":0,"Logo":"/Portals/0/StaticData/ListedCompanies/LogoEmiten/MFIN.jpg"},{"Alamat":"GRHA 9 Lt. 6, Jl. Panataran No. 9, Proklamasi, Kel. Pegangsaan, Kec. Menteng, Kota Adm. Jakarta Pusat, Provinsi DKI Jakarta, Kode Pos: 10320","BAE":"PT. Sinartama Gunita","DataID":0,"Divisi":null,"EfekEmiten_EBA":false,"EfekEmiten_ETF":false,"EfekEmiten_Obligasi":true,"EfekEmiten_Saham":true,"EfekEmiten_SPEI":false,"Industri":"Jasa Telekomunikasi","SubIndustri":"Jasa Telekomunikasi Kabel","Email":"corsec@moratelindo.co.id","Fax":"(021) 3142882","id":0,"JenisEmiten":null,"KegiatanUsahaUtama":"Bergerak dalam bidang aktivitas telekomunikasi dengan kabel, internet service provider,  jasa interkoneksi internet (NAP)","KodeDivisi":null,"KodeEmiten":"MORA","NamaEmiten":"PT Mora Telematika Indonesia Tbk","NPKP":"S-52PKP/WPJ.06/KP.1203/2018","NPWP":"01.973.886.3-007.000","PapanPencatatan":"Utama","Sektor":"Infrastruktur","SubSektor":"Telekomunikasi","TanggalPencatatan":"2022-08-08T00:00:00","Telepon":"(021) 31998600","Website":"www.moratelindo.co.id","Status":0,"Logo":"/Portals/0/StaticData/ListedCompanies/LogoEmiten/MORA.jpg"},{"Alamat":"Jl.Tomang Raya No. 21-23\r\nJakarta\r\n","BAE":"","DataID":0,"Divisi":null,"EfekEmiten_EBA":false,"EfekEmiten_ETF":false,"EfekEmiten_Obligasi":true,"EfekEmiten_Saham":true,"EfekEmiten_SPEI":false,"Industri":"Makanan Olahan","SubIndustri":"Makanan Olahan","Email":"Hermawan@mayora.co.id;yuni@mayora.co.id, yunimayora@yahoo.com","Fax":"565-5323","id":0,"JenisEmiten":null,"KegiatanUsahaUtama":"Industri Makanan Ringan","KodeDivisi":null,"KodeEmiten":"MYOR","NamaEmiten":"Mayora Indah Tbk","NPKP":"-","NPWP":"01.146.631.5-054.000","PapanPencatatan":"Utama","Sektor":"Barang Konsumen Primer","SubSektor":"Makanan & Minuman","TanggalPencatatan":"1990-07-04T00:00:00","Telepon":"565-53-11/20/22; 566 30-37, 619-14-99\r\n","Website":"-","Status":0,"Logo":"/Portals/0/StaticData/ListedCompanies/LogoEmiten/MYOR.jpg"},{"Alamat":"OCBC NISP Tower\r\nJl. Prof. Dr. Satrio Kav. 25\r\nJakarta 12940","BAE":"PT. Raya Saham Registra","DataID":0,"Divisi":null,"EfekEmiten_EBA":false,"EfekEmiten_ETF":false,"EfekEmiten_Obligasi":true,"EfekEmiten_Saham":true,"EfekEmiten_SPEI":false,"Industri":"Bank","SubIndustri":"Bank","Email":"corporate.secretariat@ocbcnisp.com","Fax":"(021) 57944000","id":0,"JenisEmiten":null,"KegiatanUsahaUtama":"Perbankan","KodeDivisi":null,"KodeEmiten":"NISP","NamaEmiten":"PT Bank OCBC NISP Tbk","NPKP":"","NPWP":"01.104.919.4-091.000","PapanPencatatan":"Utama","Sektor":"Keuangan","SubSektor":"Bank","TanggalPencatatan":"1994-10-20T00:00:00","Telepon":"(021) 25533888 ","Website":"www.ocbcnisp.com","Status":0,"Logo":"/Portals/0/StaticData/ListedCompanies/LogoEmiten/NISP.jpg"},{"Alamat":"Generali Tower, Gran Rubina Business Park Lt.17 D, Kawasan Rasuna Epicentrum, Jl.HR Rasuna Said, ","BAE":"","DataID":0,"Divisi":null,"EfekEmiten_EBA":false,"EfekEmiten_ETF":false,"EfekEmiten_Obligasi":true,"EfekEmiten_Saham":true,"EfekEmiten_SPEI":false,"Industri":"Produk Makanan Pertanian","SubIndustri":"Perkebunan & Tanaman Pangan","Email":"investor.relation@provident-agro.com ","Fax":"(021) 2157 2009 ","id":0,"JenisEmiten":null,"KegiatanUsahaUtama":"Aktivitas Perusahaan Holding dan Aktivitas Konsultasi Manajemen Lainnya ","KodeDivisi":null,"KodeEmiten":"PALM","NamaEmiten":"PT Provident Investasi Bersama Tbk","NPKP":"-","NPWP":"02.626.313.7-054.000 ","PapanPencatatan":"Pengembangan","Sektor":"Barang Konsumen Primer","SubSektor":"Makanan & Minuman","TanggalPencatatan":"2012-10-08T00:00:00","Telepon":"(021) 2157 2008","Website":"www.provident-agro.com ","Status":0,"Logo":"/Portals/0/StaticData/ListedCompanies/LogoEmiten/PALM.jpg"},{"Alamat":"Ecovention Building-Ecopark\r\nJl Lodan Timur No.7\r\nTaman Impian Jaya Ancol\r\nJakarta 14430","BAE":"","DataID":0,"Divisi":null,"EfekEmiten_EBA":false,"EfekEmiten_ETF":false,"EfekEmiten_Obligasi":true,"EfekEmiten_Saham":true,"EfekEmiten_SPEI":false,"Industri":"Pariwisata & Rekreasi","SubIndustri":"Fasilitas Rekreasi & Olah Raga","Email":"investor@ancol.com","Fax":"021-6452986; 021-64710502","id":0,"JenisEmiten":null,"KegiatanUsahaUtama":"Pengembang Kawasan Properti Komersial","KodeDivisi":null,"KodeEmiten":"PJAA","NamaEmiten":"Pembangunan Jaya Ancol Tbk","NPKP":"","NPWP":"01.300.238.1-054.000","PapanPencatatan":"Utama","Sektor":"Barang Konsumen Non-Primer","SubSektor":"Jasa Konsumen","TanggalPencatatan":"2004-07-02T00:00:00","Telepon":"021-6454567; 021-6453456","Website":"www.ancol.com","Status":0,"Logo":"/Portals/0/StaticData/ListedCompanies/LogoEmiten/PJAA.jpg"},{"Alamat":"Panin Bank Center, Jl.Jend.Sudirman - Senayan, Jakarta 10270","BAE":"","DataID":0,"Divisi":null,"EfekEmiten_EBA":false,"EfekEmiten_ETF":false,"EfekEmiten_Obligasi":true,"EfekEmiten_Saham":true,"EfekEmiten_SPEI":false,"Industri":"Bank","SubIndustri":"Bank","Email":"panin@panin.co.id","Fax":"021-2700340","id":0,"JenisEmiten":null,"KegiatanUsahaUtama":"Jasa Perbankan ","KodeDivisi":null,"KodeEmiten":"PNBN","NamaEmiten":"Bank Pan Indonesia Tbk","NPKP":"","NPWP":"01.312.166.0-091.000","PapanPencatatan":"Utama","Sektor":"Keuangan","SubSektor":"Bank","TanggalPencatatan":"1982-12-29T00:00:00","Telepon":"021-5735555 / 021-2700545","Website":"www.panin.co.id","Status":0,"Logo":"/Portals/0/StaticData/ListedCompanies/LogoEmiten/PNBN.jpg"},{"Alamat":"Plaza PP Jl. TB Simatupang No.57 Pasar Rebo, Jakarta 13760","BAE":"","DataID":0,"Divisi":null,"EfekEmiten_EBA":false,"EfekEmiten_ETF":false,"EfekEmiten_Obligasi":true,"EfekEmiten_Saham":true,"EfekEmiten_SPEI":false,"Industri":"Konstruksi Bangunan","SubIndustri":"Konstruksi Bangunan","Email":"headoffice@pp-presisi.co.id","Fax":"0218230353","id":0,"JenisEmiten":null,"KegiatanUsahaUtama":"Konstruksi, Engineering Procurement & Construction (EPC), pekerjaan mekanikal-elektrical, jasa transportasi/angkutan, jasa penyewaan, perdagangan, pertambangan.","KodeDivisi":null,"KodeEmiten":"PPRE","NamaEmiten":"PT PP Presisi Tbk.","NPKP":"","NPWP":"02.378.927.4-007.000","PapanPencatatan":"Utama","Sektor":"Infrastruktur","SubSektor":"Konstruksi Bangunan","TanggalPencatatan":"2017-11-24T00:00:00","Telepon":"0218414119","Website":"www.pp-presisi.co.id","Status":0,"Logo":"/Portals/0/StaticData/ListedCompanies/LogoEmiten/PPRE.jpg"},{"Alamat":"Plaza PP – Gedung Wisma Subiyanto, Lantai 2\r\nJl. Letjend TB. Simatupang No.57 Pasar Rebo\r\nJakarta 13760","BAE":"","DataID":0,"Divisi":null,"EfekEmiten_EBA":false,"EfekEmiten_ETF":false,"EfekEmiten_Obligasi":true,"EfekEmiten_Saham":true,"EfekEmiten_SPEI":false,"Industri":"Pengelola & Pengembang Real Estat","SubIndustri":"Pengembang & Operator Real Estat","Email":"investor.relations@pp-properti.com","Fax":"(021) 8415 606","id":0,"JenisEmiten":null,"KegiatanUsahaUtama":"Real Estate","KodeDivisi":null,"KodeEmiten":"PPRO","NamaEmiten":"PT PP Properti Tbk.","NPKP":"","NPWP":"03.276.313.8-093.000","PapanPencatatan":"Utama","Sektor":"Properti & Real Estat","SubSektor":"Properti & Real Estat","TanggalPencatatan":"2015-05-19T00:00:00","Telepon":"(021) 8779 2734","Website":"www.pp-properti.com ","Status":0,"Logo":"/Portals/0/StaticData/ListedCompanies/LogoEmiten/PPRO.jpg"},{"Alamat":"-","BAE":"","DataID":0,"Divisi":null,"EfekEmiten_EBA":false,"EfekEmiten_ETF":false,"EfekEmiten_Obligasi":true,"EfekEmiten_Saham":true,"EfekEmiten_SPEI":false,"Industri":"Logam & Mineral","SubIndustri":"Emas","Email":"-","Fax":"(021) 5153759","id":0,"JenisEmiten":null,"KegiatanUsahaUtama":"Pertambangan Emas","KodeDivisi":null,"KodeEmiten":"PSAB","NamaEmiten":"J RESOURCES ASIA PASIFIK Tbk","NPKP":"-","NPWP":"-","PapanPencatatan":"Pengembangan","Sektor":"Barang Baku","SubSektor":"Barang Baku","TanggalPencatatan":"2003-04-22T00:00:00","Telepon":"(021) 5153335","Website":"-","Status":0,"Logo":"/Portals/0/StaticData/ListedCompanies/LogoEmiten/PSAB.jpg"},{"Alamat":"Plaza PP\r\nJl. Letjend. TB Simatupang No.57\r\nPasar Rebo - Jakarta 13760","BAE":"","DataID":0,"Divisi":null,"EfekEmiten_EBA":false,"EfekEmiten_ETF":false,"EfekEmiten_Obligasi":true,"EfekEmiten_Saham":true,"EfekEmiten_SPEI":false,"Industri":"Konstruksi Bangunan","SubIndustri":"Konstruksi Bangunan","Email":"corsec@ptpp.co.id","Fax":"021-8403890","id":0,"JenisEmiten":null,"KegiatanUsahaUtama":"Jasa Konstruksi","KodeDivisi":null,"KodeEmiten":"PTPP","NamaEmiten":"PP (Persero) Tbk","NPKP":"","NPWP":"01.001.613.7-093.000","PapanPencatatan":"Utama","Sektor":"Infrastruktur","SubSektor":"Konstruksi Bangunan","TanggalPencatatan":"2010-02-09T00:00:00","Telepon":"021-8403883","Website":"www.ptpp.co.id","Status":0,"Logo":"/Portals/0/StaticData/ListedCompanies/LogoEmiten/PTPP.jpg"},{"Alamat":"Sinarmas MSIG Tower, Lantai 12 Jl. Jendral Sudirman Kav. 21, RT10/RW1, Kuningan, Karet, Kec. Setiabudi, Jakarta Selatan 12920","BAE":"","DataID":0,"Divisi":null,"EfekEmiten_EBA":false,"EfekEmiten_ETF":false,"EfekEmiten_Obligasi":true,"EfekEmiten_Saham":true,"EfekEmiten_SPEI":false,"Industri":"Farmasi","SubIndustri":"Farmasi","Email":"corsec@pyfa.co.id","Fax":"-","id":0,"JenisEmiten":null,"KegiatanUsahaUtama":"Farmasi","KodeDivisi":null,"KodeEmiten":"PYFA","NamaEmiten":"Pyridam Farma Tbk","NPKP":"","NPWP":"01.313.863.1-054.000","PapanPencatatan":"Pengembangan","Sektor":"Kesehatan","SubSektor":"Farmasi & Riset Kesehatan","TanggalPencatatan":"2001-10-16T00:00:00","Telepon":"(+6221) 50991067","Website":"www.pyfa.co.id","Status":0,"Logo":"/Portals/0/StaticData/ListedCompanies/LogoEmiten/PYFA.jpg"},{"Alamat":"Jl. Sawah Lio II No. 29-37\r\nJakarta\r\n","BAE":"PT. Raya Saham Registrar (dulu bernama PT. Risjad Salim Registra","DataID":0,"Divisi":null,"EfekEmiten_EBA":false,"EfekEmiten_ETF":false,"EfekEmiten_Obligasi":true,"EfekEmiten_Saham":true,"EfekEmiten_SPEI":false,"Industri":"","SubIndustri":"","Email":"rpg@cbn.net.id","Fax":"(021) 633-8642; 6332246","id":0,"JenisEmiten":null,"KegiatanUsahaUtama":"Industri Pakaian Jadi","KodeDivisi":null,"KodeEmiten":"RICY","NamaEmiten":"Ricky Putra Globalindo Tbk","NPKP":"","NPWP":"01.319.696.9-054.000","PapanPencatatan":"UTAMA","Sektor":"MISCELLANEOUS INDUSTRY","SubSektor":"TEXTILE, GARMENT","TanggalPencatatan":"1998-01-22T00:00:00","Telepon":"(021) 634-37-35 (Direct) 634-23-30, 632-77-70 (24 Lines)","Website":"","Status":0,"Logo":"/Portals/0/StaticData/ListedCompanies/LogoEmiten/RICY.jpg"},{"Alamat":"Jl. Selayar Blok A9, Kawasan Industri MM2100, Desa Mekarwangi, Cikarang Barat, Bekasi, Jawa Barat 17530","BAE":"","DataID":0,"Divisi":null,"EfekEmiten_EBA":false,"EfekEmiten_ETF":false,"EfekEmiten_Obligasi":true,"EfekEmiten_Saham":true,"EfekEmiten_SPEI":false,"Industri":"Makanan Olahan","SubIndustri":"Makanan Olahan","Email":"corporate.secretary@sariroti.com","Fax":"021- 89844955","id":0,"JenisEmiten":null,"KegiatanUsahaUtama":"Industri Makanan dan Minuman","KodeDivisi":null,"KodeEmiten":"ROTI","NamaEmiten":"PT Nippon Indosari Corpindo Tbk","NPKP":"","NPWP":"01.070.996.2-054.000","PapanPencatatan":"Utama","Sektor":"Barang Konsumen Primer","SubSektor":"Makanan & Minuman","TanggalPencatatan":"2010-06-28T00:00:00","Telepon":"021- 89983876, 89844953","Website":"www.sariroti.com","Status":0,"Logo":"/Portals/0/StaticData/ListedCompanies/LogoEmiten/ROTI.jpg"},{"Alamat":"Gedung Treasury Tower Lt. 26 & 27\r\nDistrict 8, SCBD Lot. 28\r\nJl. Jend. Sudirman Kav. 52 - 53\r\nJakarta ","BAE":"PT. Sinartama Gunita","DataID":0,"Divisi":null,"EfekEmiten_EBA":false,"EfekEmiten_ETF":false,"EfekEmiten_Obligasi":true,"EfekEmiten_Saham":true,"EfekEmiten_SPEI":false,"Industri":"Bank","SubIndustri":"Bank","Email":"saudara@bankwoorisaudara.com","Fax":"(62-21) 50871900","id":0,"JenisEmiten":null,"KegiatanUsahaUtama":"Perbankan","KodeDivisi":null,"KodeEmiten":"SDRA","NamaEmiten":"PT Bank Woori Saudara Indonesia 1906 Tbk","NPKP":"","NPWP":"01.148.782.4-054.000","PapanPencatatan":"Utama","Sektor":"Keuangan","SubSektor":"Bank","TanggalPencatatan":"2006-12-15T00:00:00","Telepon":"(62-21) 50871906","Website":"www.bankwoorisaudara.com","Status":0,"Logo":"/Portals/0/StaticData/ListedCompanies/LogoEmiten/SDRA.jpg"},{"Alamat":"Sampoerna Strategic Square\r\nNorth, Lt. 28\r\nJl. Jend. Sudirman Kav. 45\r\nJakarta 12930","BAE":"","DataID":0,"Divisi":null,"EfekEmiten_EBA":false,"EfekEmiten_ETF":false,"EfekEmiten_Obligasi":true,"EfekEmiten_Saham":true,"EfekEmiten_SPEI":false,"Industri":"Produk Makanan Pertanian","SubIndustri":"Perkebunan & Tanaman Pangan","Email":"eris.ariaman@sampoernaagro.com","Fax":"021-577 1712","id":0,"JenisEmiten":null,"KegiatanUsahaUtama":"Agriculture Plantation","KodeDivisi":null,"KodeEmiten":"SGRO","NamaEmiten":"PT Sampoerna Agro Tbk","NPKP":"01.598.906.4-054-000","NPWP":"01.598.906.4-054-000","PapanPencatatan":"Utama","Sektor":"Barang Konsumen Primer","SubSektor":"Makanan & Minuman","TanggalPencatatan":"2007-06-18T00:00:00","Telepon":"021-577 1711","Website":"www.sampoernaagro.com","Status":0,"Logo":"/Portals/0/StaticData/ListedCompanies/LogoEmiten/SGRO.jpg"},{"Alamat":"Gedung Sinar Mas Land Plaza, Menara 2 Lt. 28-30, Jl. MH. Thamrin No. 51, RT 09 RW 04, Gondangdia, Menteng, Jakarta Pusat, DKI Jakarta 10350","BAE":"","DataID":0,"Divisi":null,"EfekEmiten_EBA":false,"EfekEmiten_ETF":false,"EfekEmiten_Obligasi":true,"EfekEmiten_Saham":true,"EfekEmiten_SPEI":false,"Industri":"Produk Makanan Pertanian","SubIndustri":"Perkebunan & Tanaman Pangan","Email":"investor@smart-tbk.com; jimmy.pramono@sinarmas-agri.com","Fax":"-","id":0,"JenisEmiten":null,"KegiatanUsahaUtama":"Agribisnis","KodeDivisi":null,"KodeEmiten":"SMAR","NamaEmiten":"PT Sinar Mas Agro Resources and Technology Tbk","NPKP":"S237PKP/WPJ.19/KP.0203/2018","NPWP":"01.000.183.2-092.000","PapanPencatatan":"Pengembangan","Sektor":"Barang Konsumen Primer","SubSektor":"Makanan & Minuman","TanggalPencatatan":"1992-11-20T00:00:00","Telepon":"021-50338899","Website":"https://www.smart-tbk.com","Status":0,"Logo":"/Portals/0/StaticData/ListedCompanies/LogoEmiten/SMAR.jpg"},{"Alamat":"South Quarter Tower A, LT. 19-20 Jl. RA Kartini, Kav. 8, Jakarta Selatan 12430","BAE":"","DataID":0,"Divisi":null,"EfekEmiten_EBA":false,"EfekEmiten_ETF":false,"EfekEmiten_Obligasi":true,"EfekEmiten_Saham":true,"EfekEmiten_SPEI":false,"Industri":"Material Konstruksi","SubIndustri":"Material Konstruksi","Email":"corporate.secretary@sig.id; investor.relations@sig.id","Fax":"(021) 5261176","id":0,"JenisEmiten":null,"KegiatanUsahaUtama":"Produsen Semen","KodeDivisi":null,"KodeEmiten":"SMGR","NamaEmiten":"Semen Indonesia (Persero) Tbk","NPKP":"","NPWP":"01.001.631.9-051.000","PapanPencatatan":"Utama","Sektor":"Barang Baku","SubSektor":"Barang Baku","TanggalPencatatan":"1991-07-08T00:00:00","Telepon":"(021) 5261174; (021) 5261175","Website":"www.sig.id","Status":0,"Logo":"/Portals/0/StaticData/ListedCompanies/LogoEmiten/SMGR.jpg"},{"Alamat":"Menara Tekno Lantai 7 Jalan Fachruddin Nomor 19 Jakarta Pusat 10250","BAE":"","DataID":0,"Divisi":null,"EfekEmiten_EBA":false,"EfekEmiten_ETF":false,"EfekEmiten_Obligasi":true,"EfekEmiten_Saham":true,"EfekEmiten_SPEI":false,"Industri":"Perusahaan Holding & Investasi","SubIndustri":"Perusahaan Holding Keuangan","Email":"multiartha@smma.co.id ","Fax":"( 021 ) 3925788 ","id":0,"JenisEmiten":null,"KegiatanUsahaUtama":"Investment Company","KodeDivisi":null,"KodeEmiten":"SMMA","NamaEmiten":"PT Sinar Mas Multiartha Tbk","NPKP":"S-126PKP/WPJ.07/KP.0803/2019 ","NPWP":"013620026054000 ","PapanPencatatan":"Utama","Sektor":"Keuangan","SubSektor":"Perusahaan Holding & Investasi","TanggalPencatatan":"1995-07-05T00:00:00","Telepon":"( 021 ) 3925660 ","Website":"www.smma.co.id ","Status":0,"Logo":"/Portals/0/StaticData/ListedCompanies/LogoEmiten/SMMA.jpg"},{"Alamat":"Jl. Perintis Kemerdekaan No.42\r\nJakarta Timur\r\n","BAE":"","DataID":0,"Divisi":null,"EfekEmiten_EBA":false,"EfekEmiten_ETF":false,"EfekEmiten_Obligasi":true,"EfekEmiten_Saham":true,"EfekEmiten_SPEI":false,"Industri":"Pengelola & Pengembang Real Estat","SubIndustri":"Pengembang & Operator Real Estat","Email":"corp_secretary@summarecon.com","Fax":"021 - 4892976","id":0,"JenisEmiten":null,"KegiatanUsahaUtama":"Property dan Real Estate","KodeDivisi":null,"KodeEmiten":"SMRA","NamaEmiten":"PT Summarecon Agung Tbk","NPKP":"","NPWP":"01.002.261.4-054.000","PapanPencatatan":"Utama","Sektor":"Properti & Real Estat","SubSektor":"Properti & Real Estat","TanggalPencatatan":"1990-05-07T00:00:00","Telepon":"021 - 4714567","Website":"www.summarecon.com","Status":0,"Logo":"/Portals/0/StaticData/ListedCompanies/LogoEmiten/SMRA.jpg"},{"Alamat":"Jl. Honoris Raya Kav.6 Kota Modern (Modernland). Kota Tangerang 15117","BAE":"","DataID":0,"Divisi":null,"EfekEmiten_EBA":false,"EfekEmiten_ETF":false,"EfekEmiten_Obligasi":true,"EfekEmiten_Saham":true,"EfekEmiten_SPEI":false,"Industri":"Penyedia Jasa Kesehatan","SubIndustri":"Penyedia Jasa Kesehatan","Email":"chandra.rahardja@mayapadahospital.com","Fax":"021-5529036/5529420","id":0,"JenisEmiten":null,"KegiatanUsahaUtama":"Penyelenggaraan Rumah Sakit","KodeDivisi":null,"KodeEmiten":"SRAJ","NamaEmiten":"Sejahteraraya Anugrahjaya Tbk","NPKP":"0","NPWP":"01.562.139.4-415.000","PapanPencatatan":"Utama","Sektor":"Kesehatan","SubSektor":"Jasa & Peralatan Kesehatan","TanggalPencatatan":"2011-04-11T00:00:00","Telepon":"021-55781888","Website":"www.mayapadahospital.com","Status":0,"Logo":"/Portals/0/StaticData/ListedCompanies/LogoEmiten/SRAJ.jpg"},{"Alamat":"Tempo Scan Tower Lantai 20\r\nJl. HR rasuna Said Kavling 3-4 Jakarta Selatan ","BAE":"","DataID":0,"Divisi":null,"EfekEmiten_EBA":false,"EfekEmiten_ETF":false,"EfekEmiten_Obligasi":true,"EfekEmiten_Saham":true,"EfekEmiten_SPEI":false,"Industri":"Konstruksi Bangunan","SubIndustri":"Konstruksi Bangunan","Email":"inquiry@suryainternusa.com","Fax":"(62-21) 526 7878","id":0,"JenisEmiten":null,"KegiatanUsahaUtama":"Property dan Real Estate","KodeDivisi":null,"KodeEmiten":"SSIA","NamaEmiten":"PT Surya Semesta Internusa Tbk","NPKP":"","NPWP":"01.302.653.9-054.000","PapanPencatatan":"Utama","Sektor":"Infrastruktur","SubSektor":"Konstruksi Bangunan","TanggalPencatatan":"1997-03-27T00:00:00","Telepon":"(62-21) 526 2121, 527 2121","Website":"www.suryainternusa.com","Status":0,"Logo":"/Portals/0/StaticData/ListedCompanies/LogoEmiten/SSIA.jpg"},{"Alamat":"Jl. Tambak Sawah No. 21-23 Waru Sidoarjo 61256","BAE":"","DataID":0,"Divisi":null,"EfekEmiten_EBA":false,"EfekEmiten_ETF":false,"EfekEmiten_Obligasi":true,"EfekEmiten_Saham":true,"EfekEmiten_SPEI":false,"Industri":"Makanan Olahan","SubIndustri":"Makanan Olahan","Email":"corp_sec@siantartop.co.id","Fax":"(031) 866-7380, 867-3832","id":0,"JenisEmiten":null,"KegiatanUsahaUtama":"Industri Makanan Ringan","KodeDivisi":null,"KodeEmiten":"STTP","NamaEmiten":"PT Siantar Top Tbk","NPKP":"S-76PKP/WPJ.07?KP.0803/2019","NPWP":"01.480.208.6-054.000","PapanPencatatan":"Pengembangan","Sektor":"Barang Konsumen Primer","SubSektor":"Makanan & Minuman","TanggalPencatatan":"1996-12-16T00:00:00","Telepon":"(031) 866-73-82, 868-41-01, 868-11-15, 866-64-80","Website":"www.siantartop.co.id","Status":0,"Logo":"/Portals/0/StaticData/ListedCompanies/LogoEmiten/STTP.jpg"},{"Alamat":"Jln. Taman Sari IV No.12A Maphar, Taman Sari, Jakarta - 11160","BAE":"","DataID":0,"Divisi":null,"EfekEmiten_EBA":false,"EfekEmiten_ETF":false,"EfekEmiten_Obligasi":true,"EfekEmiten_Saham":true,"EfekEmiten_SPEI":false,"Industri":"Pengangkutan Darat Penumpang","SubIndustri":"Transportasi Jalanan","Email":"investor.relation@expressgroup.co.id","Fax":"(021) 29489472","id":0,"JenisEmiten":null,"KegiatanUsahaUtama":"Pengangkutan Darat","KodeDivisi":null,"KodeEmiten":"TAXI","NamaEmiten":"Express Transindo Utama Tbk","NPKP":"0","NPWP":"01.385.845.1-054.000","PapanPencatatan":"Utama","Sektor":"Transportasi & Logistik","SubSektor":"Transportasi","TanggalPencatatan":"2012-11-02T00:00:00","Telepon":"(021) 29489472","Website":"www.expressgroup.co.id","Status":0,"Logo":"/Portals/0/StaticData/ListedCompanies/LogoEmiten/TAXI.jpg"},{"Alamat":"Gedung The Convergence Indonesia, Lt. 11, Kaw. Rasuna Epicentrum, Jl. HR. Rasuna Said, Jkt-Selatan ","BAE":"","DataID":0,"Divisi":null,"EfekEmiten_EBA":false,"EfekEmiten_ETF":false,"EfekEmiten_Obligasi":true,"EfekEmiten_Saham":true,"EfekEmiten_SPEI":false,"Industri":"Jasa Telekomunikasi Nirkabel","SubIndustri":"Jasa Telekomunikasi Nirkabel","Email":"corporate.secretary@tower-bersama.com","Fax":"+62 21 2157 2015","id":0,"JenisEmiten":null,"KegiatanUsahaUtama":"Penyedia jasa infrastruktur telekomunikasi terintegrasi melalui anak perusahaan","KodeDivisi":null,"KodeEmiten":"TBIG","NamaEmiten":"PT Tower Bersama Infrastructure Tbk","NPKP":"PEM-02113/WPJ.04/KP.0103/2010","NPWP":"02.388.753.2-054.000","PapanPencatatan":"Utama","Sektor":"Infrastruktur","SubSektor":"Telekomunikasi","TanggalPencatatan":"2010-10-26T00:00:00","Telepon":"+62 21 2924 8900","Website":"http://www.tower-bersama.com","Status":0,"Logo":"/Portals/0/StaticData/ListedCompanies/LogoEmiten/TBIG.jpg"},{"Alamat":"Wisma Budi Lt. 8-9 Jl. HR. Rasuna Said Kav.C-6,Karet Kuningan, Setia Budi, Kota ADM Jakarta Selatan, DKI Jakarta 12940","BAE":"","DataID":0,"Divisi":null,"EfekEmiten_EBA":false,"EfekEmiten_ETF":false,"EfekEmiten_Obligasi":true,"EfekEmiten_Saham":true,"EfekEmiten_SPEI":false,"Industri":"Makanan Olahan","SubIndustri":"Makanan Olahan","Email":"corsec@sungaibudi.com;hardy.tbl@sungaibudi.com, dewi.effendy@sungaibudi.com","Fax":"021-5213392, 5205829","id":0,"JenisEmiten":null,"KegiatanUsahaUtama":"Agriculture Plantation","KodeDivisi":null,"KodeEmiten":"TBLA","NamaEmiten":"Tunas Baru Lampung Tbk","NPKP":"0","NPWP":"01.139.219.8-054.000","PapanPencatatan":"Utama","Sektor":"Barang Konsumen Primer","SubSektor":"Makanan & Minuman","TanggalPencatatan":"2000-02-14T00:00:00","Telepon":"021-5213383","Website":"http://www.tunasbarulampung.com ","Status":0,"Logo":"/Portals/0/StaticData/ListedCompanies/LogoEmiten/TBLA.jpg"},{"Alamat":"Gedung Mayapada Tower II, Lantai 8, Jl. Jend. Sudirman Kav. 27, Jakarta Selatan 12920 - Indonesia","BAE":"","DataID":0,"Divisi":null,"EfekEmiten_EBA":false,"EfekEmiten_ETF":false,"EfekEmiten_Obligasi":true,"EfekEmiten_Saham":true,"EfekEmiten_SPEI":false,"Industri":"Barang Kimia","SubIndustri":"Barang Kimia Dasar","Email":"corsec@tridomainmaterial.com","Fax":"(+62-21) 571 2678","id":0,"JenisEmiten":null,"KegiatanUsahaUtama":"Produsen bahan baku khusus (specialty materials) untuk berbagai industri","KodeDivisi":null,"KodeEmiten":"TDPM","NamaEmiten":"PT Tridomain Performance Materials Tbk.","NPKP":"","NPWP":"02.194.180.2-058.000","PapanPencatatan":"Pengembangan","Sektor":"Barang Baku","SubSektor":"Barang Baku","TanggalPencatatan":"2018-04-09T00:00:00","Telepon":"(+62-21) 571 2998","Website":"www.tridomainmaterial.com","Status":0,"Logo":"/Portals/0/StaticData/ListedCompanies/LogoEmiten/TDPM.jpg"},{"Alamat":"District 8 SCBD,\r\nTreasury Tower Lt. 15 H\r\nJl. Jend. Sudirman Lot 28, Kav. 52-53\r\nSudirman Central Business District (SCBD)","BAE":"PT. Adimitra Jasa Korpora","DataID":0,"Divisi":null,"EfekEmiten_EBA":false,"EfekEmiten_ETF":false,"EfekEmiten_Obligasi":true,"EfekEmiten_Saham":true,"EfekEmiten_SPEI":false,"Industri":"Batu Bara","SubIndustri":"Distribusi Batu Bara","Email":"corsec@tebe.co.id","Fax":"(021) 5010 6299","id":0,"JenisEmiten":null,"KegiatanUsahaUtama":"Konsultasi manajemen lainnya, antara lainmelakukan penyertaan modal dalam proyek dan/atau perusahaan infrastruktur","KodeDivisi":null,"KodeEmiten":"TEBE","NamaEmiten":"PT Dana Brata Luhur Tbk.","NPKP":"","NPWP":"02.742.141.1-019.000","PapanPencatatan":"Utama","Sektor":"Energi","SubSektor":"Minyak, Gas & Batu Bara","TanggalPencatatan":"2019-11-18T00:00:00","Telepon":"(021) 5010 6300","Website":"www.tebe.co.id","Status":0,"Logo":"/Portals/0/StaticData/ListedCompanies/LogoEmiten/TEBE.jpg"},{"Alamat":"Telesindo Tower, Jl. Gajah Mada No. 27 A Krukut - Tamansari, Jakarta Barat 11140","BAE":"","DataID":0,"Divisi":null,"EfekEmiten_EBA":false,"EfekEmiten_ETF":false,"EfekEmiten_Obligasi":true,"EfekEmiten_Saham":true,"EfekEmiten_SPEI":false,"Industri":"Distributor Barang Konsumen","SubIndustri":"Distributor Barang Konsumen","Email":"semuel@tiphonemobile.com","Fax":"021 - 29828282, 6496484, 6490569","id":0,"JenisEmiten":null,"KegiatanUsahaUtama":"Perdagangan Umum","KodeDivisi":null,"KodeEmiten":"TELE","NamaEmiten":"PT Omni Inovasi Indonesia Tbk","NPKP":"0","NPWP":"02.566.874.0-074.000","PapanPencatatan":"Pengembangan","Sektor":"Barang Konsumen Non-Primer","SubSektor":"Perdagangan Ritel","TanggalPencatatan":"2012-01-12T00:00:00","Telepon":"021 - 299 99 999","Website":"www.tiphonemobile.com","Status":0,"Logo":"/Portals/0/StaticData/ListedCompanies/LogoEmiten/TELE.jpg"},{"Alamat":"Jl. Medan Merdeka Timur No. 15 \r\nJakarta 10110 Indonesia","BAE":"","DataID":0,"Divisi":null,"EfekEmiten_EBA":false,"EfekEmiten_ETF":false,"EfekEmiten_Obligasi":true,"EfekEmiten_Saham":true,"EfekEmiten_SPEI":false,"Industri":"Logam & Mineral","SubIndustri":"Logam & Mineral Lainnya","Email":"InvestorRelation@pttimah.co.id","Fax":"021-2352 8080","id":0,"JenisEmiten":null,"KegiatanUsahaUtama":"Metal and Mineral Mining ","KodeDivisi":null,"KodeEmiten":"TINS","NamaEmiten":"PT Timah Tbk. ","NPKP":"01.001.665.7-051.000","NPWP":"01.001.665.7-051.000","PapanPencatatan":"Utama","Sektor":"Barang Baku","SubSektor":"Barang Baku","TanggalPencatatan":"1995-10-19T00:00:00","Telepon":"021-2352 8000","Website":"www.timah.com","Status":0,"Logo":"/Portals/0/StaticData/ListedCompanies/LogoEmiten/TINS.jpg"},{"Alamat":"Gedung Prima Office Tower (The Bellezza) 20th Floor.\r\nJl. Let.Jend. Soepeno No. 34. Jakarta Selatan","BAE":"PT. Adimitra Jasa Korpora","DataID":0,"Divisi":null,"EfekEmiten_EBA":false,"EfekEmiten_ETF":false,"EfekEmiten_Obligasi":true,"EfekEmiten_Saham":true,"EfekEmiten_SPEI":false,"Industri":"Perhutanan & Kertas","SubIndustri":"Kayu","Email":"corpsecretary@tirtamahakam.com;","Fax":"021-25675714, 021-25675715, 021-25675716","id":0,"JenisEmiten":null,"KegiatanUsahaUtama":"Wood Industries ","KodeDivisi":null,"KodeEmiten":"TIRT","NamaEmiten":"Tirta Mahakam Resources Tbk","NPKP":"","NPWP":"01.001.792.9-054.000","PapanPencatatan":"Pengembangan","Sektor":"Barang Baku","SubSektor":"Barang Baku","TanggalPencatatan":"1999-12-13T00:00:00","Telepon":"021-25675717","Website":"http://www.tirtamahakam.com","Status":0,"Logo":"/Portals/0/StaticData/ListedCompanies/LogoEmiten/TIRT.jpg"},{"Alamat":"Telkom Landmark Tower, Lantai 39","BAE":"","DataID":0,"Divisi":null,"EfekEmiten_EBA":false,"EfekEmiten_ETF":false,"EfekEmiten_Obligasi":true,"EfekEmiten_Saham":true,"EfekEmiten_SPEI":false,"Industri":"Jasa Telekomunikasi","SubIndustri":"Jasa Telekomunikasi Terintegrasi","Email":"investor@telkom.co.id","Fax":"(021) 5220500","id":0,"JenisEmiten":null,"KegiatanUsahaUtama":"Penyelenggara Jaringan dan Jasa Telekom","KodeDivisi":null,"KodeEmiten":"TLKM","NamaEmiten":"PT Telkom Indonesia (Persero) Tbk","NPKP":"","NPWP":"01.000.013.1-093.000","PapanPencatatan":"Utama","Sektor":"Infrastruktur","SubSektor":"Telekomunikasi","TanggalPencatatan":"1995-11-14T00:00:00","Telepon":"(021) 5215109","Website":"www.telkom.co.id","Status":0,"Logo":"/Portals/0/StaticData/ListedCompanies/LogoEmiten/TLKM.jpg"},{"Alamat":"Treasury Tower, Level 33, District 8, SCBD Lot 28 Jl. Jend Sudirman Kav. 52-53 Jakarta 12190","BAE":"","DataID":0,"Divisi":null,"EfekEmiten_EBA":false,"EfekEmiten_ETF":false,"EfekEmiten_Obligasi":true,"EfekEmiten_Saham":true,"EfekEmiten_SPEI":false,"Industri":"Batu Bara","SubIndustri":"Produksi Batu Bara","Email":"corsec@tbsenergi.com","Fax":"021-50200352","id":0,"JenisEmiten":null,"KegiatanUsahaUtama":"pertambangan batubara melalui entitas anak","KodeDivisi":null,"KodeEmiten":"TOBA","NamaEmiten":"PT TBS Energi Utama Tbk","NPKP":"-","NPWP":"02.672.081.3-054.000","PapanPencatatan":"Utama","Sektor":"Energi","SubSektor":"Minyak, Gas & Batu Bara","TanggalPencatatan":"2012-07-06T00:00:00","Telepon":"021-50200353","Website":"www.tbsenergi.com","Status":0,"Logo":"/Portals/0/StaticData/ListedCompanies/LogoEmiten/TOBA.jpg"},{"Alamat":"Gedung Wisma Barito Pacific Tower A, Lt. 7 Jl. Let Jend S. Parman Kav. 62-63 RT.008 RW.004 Slipi Palmerah. Jakarta Barat. DKI Jakarta - 11410 ","BAE":"","DataID":0,"Divisi":null,"EfekEmiten_EBA":false,"EfekEmiten_ETF":false,"EfekEmiten_Obligasi":true,"EfekEmiten_Saham":true,"EfekEmiten_SPEI":false,"Industri":"Barang Kimia","SubIndustri":"Barang Kimia Dasar","Email":"corporatesecretary@capcx.com","Fax":"(021) 5308950","id":0,"JenisEmiten":null,"KegiatanUsahaUtama":"Petrokimia","KodeDivisi":null,"KodeEmiten":"TPIA","NamaEmiten":"PT Chandra Asri Petrochemical Tbk","NPKP":"-","NPWP":"01.062.049.0-092.000","PapanPencatatan":"Pengembangan","Sektor":"Barang Baku","SubSektor":"Barang Baku","TanggalPencatatan":"2008-05-26T00:00:00","Telepon":"(021) 5307950","Website":"www.chandra-asri.com","Status":0,"Logo":"/Portals/0/StaticData/ListedCompanies/LogoEmiten/TPIA.jpg"},{"Alamat":"\tGedung Menara Karya Lantai 3 Unit D Jl HR. Rasuna Said Blok X-5, Kav. 1-2 Jakarta 12950 ","BAE":"","DataID":0,"Divisi":null,"EfekEmiten_EBA":false,"EfekEmiten_ETF":false,"EfekEmiten_Obligasi":true,"EfekEmiten_Saham":true,"EfekEmiten_SPEI":false,"Industri":"Kelistrikan","SubIndustri":"Komponen & Peralatan Kelistrikan","Email":"corsecve@voksel.com; saske.siddharta@voksel.com","Fax":"(021) 57944649 ","id":0,"JenisEmiten":null,"KegiatanUsahaUtama":"Industri Kabel","KodeDivisi":null,"KodeEmiten":"VOKS","NamaEmiten":"Voksel Electric Tbk","NPKP":"","NPWP":"01.000.784.7-054.000 ","PapanPencatatan":"Utama","Sektor":"Perindustrian","SubSektor":"Barang Perindustrian","TanggalPencatatan":"1990-12-20T00:00:00","Telepon":"(021) 57944622 ","Website":"http://www.voksel.co.id ","Status":0,"Logo":"/Portals/0/StaticData/ListedCompanies/LogoEmiten/VOKS.jpg"},{"Alamat":"Jl. D.I. Panjaitan Kav. 9-10 Jakarta 13340","BAE":"","DataID":0,"Divisi":null,"EfekEmiten_EBA":false,"EfekEmiten_ETF":false,"EfekEmiten_Obligasi":true,"EfekEmiten_Saham":true,"EfekEmiten_SPEI":false,"Industri":"Konstruksi Bangunan","SubIndustri":"Konstruksi Bangunan","Email":"adwijaya@wika.co.id","Fax":"22893830","id":0,"JenisEmiten":null,"KegiatanUsahaUtama":"Jasa Konstruksi","KodeDivisi":null,"KodeEmiten":"WIKA","NamaEmiten":"PT Wijaya Karya (Persero) Tbk","NPKP":"","NPWP":"01.001.615.2-093.000","PapanPencatatan":"Utama","Sektor":"Infrastruktur","SubSektor":"Konstruksi Bangunan","TanggalPencatatan":"2007-10-29T00:00:00","Telepon":"80679200","Website":"www.wika.co.id","Status":0,"Logo":"/Portals/0/StaticData/ListedCompanies/LogoEmiten/WIKA.jpg"},{"Alamat":"Altira Office Tower Lt. 32, 33, 35 Jl. Yos Sudarso Kav.85 RT.000, RW. 000, Kelurahan Sunter Jaya, Kecamatan Tanjung Priok, Jakarta Utara 14350","BAE":"","DataID":0,"Divisi":null,"EfekEmiten_EBA":false,"EfekEmiten_ETF":false,"EfekEmiten_Obligasi":true,"EfekEmiten_Saham":true,"EfekEmiten_SPEI":false,"Industri":"Pembiayaan Konsumen","SubIndustri":"Pembiayaan Konsumen","Email":"corporate_secretary@wom.co.id","Fax":"021 2188 2420","id":0,"JenisEmiten":null,"KegiatanUsahaUtama":"Pembiayaan","KodeDivisi":null,"KodeEmiten":"WOMF","NamaEmiten":"PT Wahana Ottomitra Multiartha Tbk","NPKP":"-","NPWP":"01.311.910.2-091.000","PapanPencatatan":"Utama","Sektor":"Keuangan","SubSektor":"Jasa Pembiayaan","TanggalPencatatan":"2004-12-13T00:00:00","Telepon":"021 2188 2400","Website":"www.wom.co.id","Status":0,"Logo":"/Portals/0/StaticData/ListedCompanies/LogoEmiten/WOMF.jpg"},{"Alamat":"Jl. Raya Betro No. 678, Sedati – Sidoarjo 61253\r\nJawa Timur – Indonesia","BAE":"","DataID":0,"Divisi":null,"EfekEmiten_EBA":false,"EfekEmiten_ETF":false,"EfekEmiten_Obligasi":true,"EfekEmiten_Saham":true,"EfekEmiten_SPEI":false,"Industri":"Barang Rumah Tangga","SubIndustri":"Produsen Furnitur Rumah","Email":"corsec.integra@iil.co.id","Fax":"+6231-8911108","id":0,"JenisEmiten":null,"KegiatanUsahaUtama":"Industri furnitur, Industri Kayu, dan menjalankan usaha dalam bidang perdagangan, termasuk perdagangan impor ekspor","KodeDivisi":null,"KodeEmiten":"WOOD","NamaEmiten":"PT Integra Indocabinet Tbk","NPKP":"","NPWP":"01.497.306.9-641.000","PapanPencatatan":"Utama","Sektor":"Barang Konsumen Non-Primer","SubSektor":"Barang Rumah Tangga","TanggalPencatatan":"2017-06-21T00:00:00","Telepon":"+6231-8910434, +6231-8910435, +6231-8910436","Website":"www.integrafurniture.co.id","Status":0,"Logo":"/Portals/0/StaticData/ListedCompanies/LogoEmiten/WOOD.jpg"},{"Alamat":"Gedung Teraskita, Lt. 3-3A\r\nJl. MT. Haryono Kav. No. 10A, RT 11, RW11, Cipinang Cempedak, Jatinegara, Jakarta Timur 13340","BAE":"","DataID":0,"Divisi":null,"EfekEmiten_EBA":false,"EfekEmiten_ETF":false,"EfekEmiten_Obligasi":true,"EfekEmiten_Saham":true,"EfekEmiten_SPEI":false,"Industri":"Material Konstruksi","SubIndustri":"Material Konstruksi","Email":"info@waskitaprecast.co.id","Fax":"(021) 29838020","id":0,"JenisEmiten":null,"KegiatanUsahaUtama":"Industri manufaktur beton precast dan ready mix","KodeDivisi":null,"KodeEmiten":"WSBP","NamaEmiten":"PT Waskita Beton Precast Tbk.","NPKP":"","NPWP":"71.207.015.0-093.000","PapanPencatatan":"Pengembangan","Sektor":"Barang Baku","SubSektor":"Barang Baku","TanggalPencatatan":"2016-09-20T00:00:00","Telepon":"(021) 22892999","Website":"www.waskitaprecast.co.id","Status":0,"Logo":"/Portals/0/StaticData/ListedCompanies/LogoEmiten/WSBP.jpg"},{"Alamat":"Jln. MT Haryono Kav. 10 Cawang, Jakarta","BAE":"","DataID":0,"Divisi":null,"EfekEmiten_EBA":false,"EfekEmiten_ETF":false,"EfekEmiten_Obligasi":true,"EfekEmiten_Saham":true,"EfekEmiten_SPEI":false,"Industri":"Konstruksi Bangunan","SubIndustri":"Konstruksi Bangunan","Email":"waskita@waskita.co.id","Fax":"21 8508506","id":0,"JenisEmiten":null,"KegiatanUsahaUtama":"Jasa Konstruksi, Industri, Realty dan Perdagangan","KodeDivisi":null,"KodeEmiten":"WSKT","NamaEmiten":"PT Waskita Karya (Persero) Tbk","NPKP":"-","NPWP":"01.001.614.5-093.000","PapanPencatatan":"Utama","Sektor":"Infrastruktur","SubSektor":"Konstruksi Bangunan","TanggalPencatatan":"2012-12-19T00:00:00","Telepon":"021 8508510","Website":"www.waskita.co.id","Status":0,"Logo":"/Portals/0/StaticData/ListedCompanies/LogoEmiten/WSKT.jpg"},{"Alamat":"Jl. Pantai Indah Selatan I, Elang Laut Blok A No. 32-33\r\nLantai 5 Jakarta 14470, Indonesia\r\n","BAE":"","DataID":0,"Divisi":null,"EfekEmiten_EBA":false,"EfekEmiten_ETF":false,"EfekEmiten_Obligasi":true,"EfekEmiten_Saham":true,"EfekEmiten_SPEI":false,"Industri":"Logam & Mineral","SubIndustri":"Logam & Mineral Lainnya","Email":"corsec@ptkpc.com","Fax":"021 - 29676234","id":0,"JenisEmiten":null,"KegiatanUsahaUtama":"Pertambangan dan Perdagangan","KodeDivisi":null,"KodeEmiten":"ZINC","NamaEmiten":"PT Kapuas Prima Coal Tbk","NPKP":"","NPWP":"02.386.972.0-091.000","PapanPencatatan":"Pengembangan","Sektor":"Barang Baku","SubSektor":"Barang Baku","TanggalPencatatan":"2017-10-16T00:00:00","Telepon":"021 - 29676236","Website":"www.ptkpc.com","Status":0,"Logo":"/Portals/0/StaticData/ListedCompanies/LogoEmiten/ZINC.jpg"}]}